serieparalelo/comparacion de modelos/serieparalelo.v
`timescale 1ns / 1ps
//////////////////////////////////////////////////////////////////////////////////
// Company: U.C.R E.I.E
// Engineer: Brandon Esquivel Molina
// 
// Create Date: 26.05.2020
// Design Name: Serial to parallel Module 
// Module Name: Serial to parallel Module 
// Project Name: PHY Layer PCIe
// Target Devices: PCIe
// Tool Versions: Yosys 0.9 Iverolg release at 2020
// Description: 
// Dependencies:
// 
// Revision: 1.0  all good 
// Revision 0.01 - File Created
// Additional Comments: 
// 
//////////////////////////////////////////////////////////////////////////////////


module serieparalelo(
    
    // INPUTS
    input wire in,                          // entradas de 1 bit a 32f
    input wire clk32f,                      // f max
    input wire clk4f,                       // f del paralelo 32f/8 datos = 4f
    input wire reset,
    // OUTPUTS
    output reg [7:0] out,
    output reg valid                            // salida dato valido
);   
    // INTERNAL/AUXILIARY
    reg [7:0] register;             // registro de datos de entrada a enviar
    reg [3:0] BC_counter;           // contador de Palabras BC 
    reg active;                     // indica comunicación activa entre los modulos
    reg valido;                      // valid del dato de salida
    
    always @( posedge clk32f ) begin
        if (~reset) begin
            register    <=  0;
        end else begin 
            register  <=  {register[6:0], in};  // registro desplazando bit a bit de entrada
        end
    end



    // POSEDGE CLKS
    always @(posedge clk4f) begin
        if (~reset) begin
            BC_counter   <=  0;          // condicion de reset para contador de BC
            valido       <=  0;          // set del valido de salida       
            out          <=  0;          // salida a cero 
        end else begin

        // contador de BC 
        if (register == 'hBC) begin
                if (~active) begin                  // si no hay active
                    BC_counter  <= BC_counter + 1;  // contador aumenta
                end
            end else begin
                BC_counter  <= BC_counter;          // se cumple la condicion de active, se mantiene BC = 4
            end

    // Condicional para valid
        if(active && register != 'hBC) begin        // si hay active y el registro indica una palabra diferente de BC
                valido = 1;                          // se valida el dato/palabra
            end else begin
                valido = 0;                          // en otro caso, no
            end

    // Salidas         
    if ( valido ) begin
        out <= register;                          // Trasegando dato
        valid <= 1;
        end else begin
            out <= out;                             // mantiene ultimo valor de salida en caso de valid = 0
            valid <= 0;
        end
    end
end

// inicia logica combinacional
always @(*) begin                   // logica para la senal de active
if(BC_counter >= 4) begin      // cuando se llega a 4 BC se activa active, en otro contador es cero, esto indica el control para el inicio de envio de palabras
    active = 1;
end else begin
     active = 0;
        end
    end

endmodule                   // serieparalelo

serieparalelo/comparacion de modelos/tester.v
//////////////////////////////////////////////////////////////////////////////////
// Company: U.C.R, EIE
// Engineer: Brandon Esquivel Molina
// 
// Create Date: 26.05.2020
// Design Name: Serial to parallel Module 
// Project Name: PHY Layer PCIe
// Target Devices: PCIe
// Tool Versions: Yosys 0.9 Iverolg release at 2020
// Description: tester for Serial to parallel module
// Dependencies: 
// 
// Revision: 1.0  All good
// Revision 0.01 - File Created
// Additional Comments: 
// 
//////////////////////////////////////////////////////////////////////////////////


module tester(
    input wire [7:0] out,           // salida paralela de bus de 8 bits + valid
    input wire [7:0] outs,  
    input wire valid,               // + valid
    output reg in,                  // entrada bit a bit serial
    output reg reset,               // reset
    output reg clk32f,              // frecuencia mas rapida, de recepcion
    output reg clk4f                // frecuencia de envio

);
    
    // AUXILIARES
    reg clk16f;
    reg clk8f;
    reg clk2f;
    reg clk1f;
    reg clk;
    
    initial begin
		$dumpfile("muxy.vcd");																						// "dump" file
	$dumpvars;
	
      repeat (6) begin
		@(posedge clk32f);	
		reset = 0;
		end		

		repeat (6) begin																							// Repeat the test 3 times
		@(posedge clk32f);																								// sync with clock																			 	
		reset = 1;
		end

        @(posedge clk32f);

        // pruebas 

        repeat(3) begin         // 01010101  -> NO HAY ACTIVE YA QUE BC < 4
        @(posedge clk32f);
        in  <=  ~in;
        end


        repeat(5) begin         // BC = 10 1111 00        
        @(posedge clk32f);
        in  <=  1;
        @(posedge clk32f);
        in  <=  0;
        @(posedge clk32f);
        in  <=  1;
        @(posedge clk32f);
        in  <=  1;
        @(posedge clk32f);
        in  <=  1;
        @(posedge clk32f);
        in  <=  1;
        @(posedge clk32f);
        in  <=  0;
        @(posedge clk32f);
        in  <=  0;
        end
        
        // EN ESTE PUNTO SE TIENEN 5 BC > ACTIVE = 1 Y SE RECIBE UNA PALABRA valida
        
             // Nueva palabra a enviar  -> FF -> 11111111
        @(posedge clk32f);
        in  <=  1;
        @(posedge clk32f);
        in  <=  1;
        @(posedge clk32f);
        in  <=  1;
        @(posedge clk32f);
        in  <=  1;
        @(posedge clk32f);
        in  <=  1;
        @(posedge clk32f);
        in  <=  1;
        @(posedge clk32f);
        in  <=  1;
        @(posedge clk32f);
        in  <=  1;

        // nueva palabra DD 11011101
        
         @(posedge clk32f);
        in  <=  1;
        @(posedge clk32f);
        in  <=  1;
        @(posedge clk32f);
        in  <=  0;
        @(posedge clk32f);
        in  <=  1;
        @(posedge clk32f);
        in  <=  1;
        @(posedge clk32f);
        in  <=  1;
        @(posedge clk32f);
        in  <=  0;
        @(posedge clk32f);
        in  <=  1;



         // Nueva palabra a enviar  -> EE -> 11101110
      @(posedge clk32f);
        in  <=  1;
        @(posedge clk32f);
        in  <=  1;
        @(posedge clk32f);
        in  <=  1;
        @(posedge clk32f);
        in  <=  0;
        @(posedge clk32f);
        in  <=  1;
        @(posedge clk32f);
        in  <=  1;
        @(posedge clk32f);
        in  <=  1;
        @(posedge clk32f);
        in  <=  0;
        
        // nueva palabra CC ->  11001100
        @(posedge clk32f);
        in  <=  1;
        @(posedge clk32f);
        in  <=  1;
        @(posedge clk32f);
        in  <=  0;
        @(posedge clk32f);
        in  <=  0;
        @(posedge clk32f);
        in  <=  1;
        @(posedge clk32f);
        in  <=  1;
        @(posedge clk32f);
        in  <=  0;
        @(posedge clk32f);
        in  <=  0;

        // NUEVA PALABRA BB -> 10111011 

        @(posedge clk32f);
        in  <=  1;
        @(posedge clk32f);
        in  <=  0;
        @(posedge clk32f);
        in  <=  1;
        @(posedge clk32f);
        in  <=  1;
        @(posedge clk32f);
        in  <=  1;
        @(posedge clk32f);
        in  <=  0;
        @(posedge clk32f);
        in  <=  1;
        @(posedge clk32f);
        in  <=  1;

        // NUEVA PALABRA 99 -> 10011001
        @(posedge clk32f);
        in  <=  1;
        @(posedge clk32f);
        in  <=  0;
        @(posedge clk32f);
        in  <=  0;
        @(posedge clk32f);
        in  <=  1;
        @(posedge clk32f);
        in  <=  1;
        @(posedge clk32f);
        in  <=  0;
        @(posedge clk32f);
        in  <=  0;
        @(posedge clk32f);
        in  <=  1;

        // NUEVA PALABRA 10101010 -> AA 
            
@(posedge clk32f);
        in  <=  1;
        @(posedge clk32f);
        in  <=  0;
        @(posedge clk32f);
        in  <=  1;
        @(posedge clk32f);
        in  <=  0;
        @(posedge clk32f);
        in  <=  1;
        @(posedge clk32f);
        in  <=  0;
        @(posedge clk32f);
        in  <=  1;
        @(posedge clk32f);
        in  <=  0;

        // Nueva palabra a enviar  -88 -> 10001000
      @(posedge clk32f);
        in  <=  1;
        @(posedge clk32f);
        in  <=  0;
        @(posedge clk32f);
        in  <=  0;
        @(posedge clk32f);
        in  <=  0;
        @(posedge clk32f);
        in  <=  1;
        @(posedge clk32f);
        in  <=  0;
        @(posedge clk32f);
        in  <=  0;
        @(posedge clk32f);
        in  <=  0;

         repeat(8) begin         
        @(posedge clk32f);
         end
       

        $finish;
    end


	// Initial Values
	initial in			= 0;	
	initial reset 		= 0;

	// clock logic
	initial	clk	 	    = 0;			// Initial value to avoid indeterminations
	always	#5 clk	    = ~clk;		// toggle every 1ns

	// clks 

	initial clk32f <= 0;
    initial clk16f <= 0;
    initial clk8f <= 0;
    initial clk4f <= 0;
    initial clk2f <= 0;
    initial clk1f <= 0;

	

	// checker
reg test;

always@(posedge clk) begin
    if(out != outs)
    begin
       $display ("ERROR behavioral file and structural file are not the same");
       test <= 1;
     end // end display

     else begin
        test <= 0;
      end //else
end // always checker



    // Faster frequency
    always @(posedge clk) begin
		clk32f <= ~clk32f; // if was LOW change to HIGH
        end 
    //////////////////////////////
    // For 16 Hz
    always @(posedge clk32f) begin
        clk16f <= ~clk16f; // if was LOW change to HIGH
        end
    //////////////////////////////
    // For 8 Hz
    always @(posedge clk16f) begin
            clk8f <= ~clk8f; // if was LOW change to HIGH
    end
    //////////////////////////////
    // For 4 Hz
    always @(posedge clk8f) begin
        clk4f <= ~clk4f; // if was LOW change to HIGH
        end
    //////////////////////////////
    // At 2 Hz
    always @(posedge clk4f) begin
        clk2f <= ~clk2f; // if was LOW change to HIGH
        end

    //////////////////////////////
    // At 1 HZ
    always @(posedge clk2f) begin
    clk1f <= ~clk1f; // if was LOW change to HIGH
 	end

endmodule // t_mux42

serieparalelo/comparacion de modelos/tb.v
`include "tester.v"
`include "serieparalelo.v"
`include "cmos_cells.v" 

module bancoPruebas();
    wire in;
    wire [7:0] out;
    wire [7:0] outs;
    wire reset;
    wire clk4f;
    wire valid;
    wire clk32f;

tester Probador(
                    .out(out),
 		            .outs(outs),
                    .in(in),
                    .clk4f(clk4f),
                    .clk32f(clk32f),
                    .reset(reset),
                    .valid(valid)
    );

serieparalelo spc (
                    .in(in),
                    .clk32f(clk32f),
                    .clk4f(clk4f),
                    .reset(reset),
                    .out(out),
                    .valid(valid)
);

serieparalelo sps (
                    .in(in),
                    .clk32f(clk32f),
                    .clk4f(clk4f),
                    .reset(reset),
                    .out(outs),
                    .valid(valid)
);
endmodule

serieparalelo/Serie paralelo/cmos_cells.v
module BUF(A, Y);
input A;
output Y;
assign  Y = A;
endmodule

module NOT(A, Y);
input A;
output Y;
assign   Y = ~A;
endmodule

module NAND(A, B, Y);
input A, B;
output Y;
assign   Y = ~(A & B);
endmodule

module NOR(A, B, Y);
input A, B;
output Y;
assign   Y = ~(A | B);
endmodule

module DFF(C, D, Q);
input C, D;
output reg Q;
always @(posedge C)
	Q <= D;
endmodule

module DFFSR(C, D, Q, S, R);
input C, D, S, R;
output reg Q;
always @(posedge C, posedge S, posedge R)
	if (S)
		Q <= 1'b1;
	else if (R)
		#6 Q <= 1'b0;
	else
		#6 Q <= D;
endmodule

serieparalelo/comparacion de modelos/muxy.vcd
$date
	Wed Jun  3 11:17:08 2020
$end
$version
	Icarus Verilog
$end
$timescale
	1ps
$end
$scope module BUF $end
$var wire 1 ! A $end
$var wire 1 " Y $end
$upscope $end
$scope module DFF $end
$var wire 1 # C $end
$var wire 1 $ D $end
$var reg 1 % Q $end
$upscope $end
$scope module DFFSR $end
$var wire 1 & C $end
$var wire 1 ' D $end
$var wire 1 ( R $end
$var wire 1 ) S $end
$var reg 1 * Q $end
$upscope $end
$scope module NAND $end
$var wire 1 + A $end
$var wire 1 , B $end
$var wire 1 - Y $end
$upscope $end
$scope module NOR $end
$var wire 1 . A $end
$var wire 1 / B $end
$var wire 1 0 Y $end
$upscope $end
$scope module NOT $end
$var wire 1 1 A $end
$var wire 1 2 Y $end
$upscope $end
$scope module bancoPruebas $end
$var wire 1 3 valid $end
$var wire 1 4 reset $end
$var wire 8 5 outs [7:0] $end
$var wire 8 6 out [7:0] $end
$var wire 1 7 in $end
$var wire 1 8 clk4f $end
$var wire 1 9 clk32f $end
$scope module Probador $end
$var wire 1 3 valid $end
$var wire 8 : outs [7:0] $end
$var wire 8 ; out [7:0] $end
$var reg 1 < clk $end
$var reg 1 = clk16f $end
$var reg 1 > clk1f $end
$var reg 1 ? clk2f $end
$var reg 1 9 clk32f $end
$var reg 1 8 clk4f $end
$var reg 1 @ clk8f $end
$var reg 1 7 in $end
$var reg 1 4 reset $end
$var reg 1 A test $end
$upscope $end
$scope module spc $end
$var wire 1 9 clk32f $end
$var wire 1 8 clk4f $end
$var wire 1 7 in $end
$var wire 1 4 reset $end
$var reg 4 B BC_counter [3:0] $end
$var reg 1 C active $end
$var reg 8 D out [7:0] $end
$var reg 8 E register [7:0] $end
$var reg 1 F valid $end
$var reg 1 G valido $end
$upscope $end
$scope module sps $end
$var wire 1 9 clk32f $end
$var wire 1 8 clk4f $end
$var wire 1 7 in $end
$var wire 1 4 reset $end
$var reg 4 H BC_counter [3:0] $end
$var reg 1 I active $end
$var reg 8 J out [7:0] $end
$var reg 8 K register [7:0] $end
$var reg 1 L valid $end
$var reg 1 M valido $end
$upscope $end
$upscope $end
$enddefinitions $end
#0
$dumpvars
xM
xL
bx K
bx J
xI
bx H
xG
xF
bx E
bx D
xC
bx B
xA
0@
0?
0>
0=
0<
bx ;
bx :
09
08
07
bx 6
bx 5
04
x3
z2
z1
x0
z/
z.
x-
z,
z+
x*
z)
z(
z'
z&
x%
z$
z#
z"
z!
$end
#5000000000000
1>
0C
0I
1?
b0 6
b0 ;
b0 D
0G
b0 B
b0 5
b0 :
b0 J
0M
b0 H
18
1@
1=
b0 E
b0 K
0A
19
1<
#10000000000000
0<
#15000000000000
09
1<
#20000000000000
0<
#25000000000000
0=
19
1<
#30000000000000
0<
#35000000000000
09
1<
#40000000000000
0<
#45000000000000
0@
1=
19
1<
#50000000000000
0<
#55000000000000
09
1<
#60000000000000
0<
#65000000000000
0=
19
1<
#70000000000000
0<
#75000000000000
09
1<
#80000000000000
0<
#85000000000000
08
1@
1=
19
1<
#90000000000000
0<
#95000000000000
09
1<
#100000000000000
0<
#105000000000000
0=
19
1<
#110000000000000
0<
#115000000000000
09
1<
#120000000000000
0<
#125000000000000
0@
1=
14
19
1<
#130000000000000
0<
#135000000000000
09
1<
#140000000000000
0<
#145000000000000
0=
19
1<
#150000000000000
0<
#155000000000000
09
1<
#160000000000000
0<
#165000000000000
03
0L
0F
0?
18
1@
1=
19
1<
#170000000000000
0<
#175000000000000
09
1<
#180000000000000
0<
#185000000000000
0=
19
1<
#190000000000000
0<
#195000000000000
09
1<
#200000000000000
0<
#205000000000000
0@
1=
19
1<
#210000000000000
0<
#215000000000000
09
1<
#220000000000000
0<
#225000000000000
0=
19
1<
#230000000000000
0<
#235000000000000
09
1<
#240000000000000
0<
#245000000000000
08
1@
1=
19
1<
#250000000000000
0<
#255000000000000
09
1<
#260000000000000
0<
#265000000000000
0=
17
19
1<
#270000000000000
0<
#275000000000000
09
1<
#280000000000000
0<
#285000000000000
0@
07
1=
b1 E
b1 K
19
1<
#290000000000000
0<
#295000000000000
09
1<
#300000000000000
0<
#305000000000000
b10 K
b10 E
0=
17
19
1<
#310000000000000
0<
#315000000000000
09
1<
#320000000000000
0<
#325000000000000
0>
1?
18
1@
1=
b101 E
b101 K
19
1<
#330000000000000
0<
#335000000000000
09
1<
#340000000000000
0<
#345000000000000
b1011 K
b1011 E
0=
07
19
1<
#350000000000000
0<
#355000000000000
09
1<
#360000000000000
0<
#365000000000000
0@
17
1=
b10110 E
b10110 K
19
1<
#370000000000000
0<
#375000000000000
09
1<
#380000000000000
0<
#385000000000000
b101101 K
b101101 E
0=
19
1<
#390000000000000
0<
#395000000000000
09
1<
#400000000000000
0<
#405000000000000
08
1@
1=
b1011011 E
b1011011 K
19
1<
#410000000000000
0<
#415000000000000
09
1<
#420000000000000
0<
#425000000000000
b10110111 K
b10110111 E
0=
19
1<
#430000000000000
0<
#435000000000000
09
1<
#440000000000000
0<
#445000000000000
0@
07
1=
b1101111 E
b1101111 K
19
1<
#450000000000000
0<
#455000000000000
09
1<
#460000000000000
0<
#465000000000000
b11011110 K
b11011110 E
0=
19
1<
#470000000000000
0<
#475000000000000
09
1<
#480000000000000
0<
#485000000000000
b1 H
b1 B
0?
18
1@
17
1=
b10111100 E
b10111100 K
19
1<
#490000000000000
0<
#495000000000000
09
1<
#500000000000000
0<
#505000000000000
b1111001 K
b1111001 E
0=
07
19
1<
#510000000000000
0<
#515000000000000
09
1<
#520000000000000
0<
#525000000000000
0@
17
1=
b11110010 E
b11110010 K
19
1<
#530000000000000
0<
#535000000000000
09
1<
#540000000000000
0<
#545000000000000
b11100101 K
b11100101 E
0=
19
1<
#550000000000000
0<
#555000000000000
09
1<
#560000000000000
0<
#565000000000000
08
1@
1=
b11001011 E
b11001011 K
19
1<
#570000000000000
0<
#575000000000000
09
1<
#580000000000000
0<
#585000000000000
b10010111 K
b10010111 E
0=
19
1<
#590000000000000
0<
#595000000000000
09
1<
#600000000000000
0<
#605000000000000
0@
07
1=
b101111 E
b101111 K
19
1<
#610000000000000
0<
#615000000000000
09
1<
#620000000000000
0<
#625000000000000
b1011110 K
b1011110 E
0=
19
1<
#630000000000000
0<
#635000000000000
09
1<
#640000000000000
0<
#645000000000000
1>
1?
b10 B
b10 H
18
1@
17
1=
b10111100 E
b10111100 K
19
1<
#650000000000000
0<
#655000000000000
09
1<
#660000000000000
0<
#665000000000000
b1111001 K
b1111001 E
0=
07
19
1<
#670000000000000
0<
#675000000000000
09
1<
#680000000000000
0<
#685000000000000
0@
17
1=
b11110010 E
b11110010 K
19
1<
#690000000000000
0<
#695000000000000
09
1<
#700000000000000
0<
#705000000000000
b11100101 K
b11100101 E
0=
19
1<
#710000000000000
0<
#715000000000000
09
1<
#720000000000000
0<
#725000000000000
08
1@
1=
b11001011 E
b11001011 K
19
1<
#730000000000000
0<
#735000000000000
09
1<
#740000000000000
0<
#745000000000000
b10010111 K
b10010111 E
0=
19
1<
#750000000000000
0<
#755000000000000
09
1<
#760000000000000
0<
#765000000000000
0@
07
1=
b101111 E
b101111 K
19
1<
#770000000000000
0<
#775000000000000
09
1<
#780000000000000
0<
#785000000000000
b1011110 K
b1011110 E
0=
19
1<
#790000000000000
0<
#795000000000000
09
1<
#800000000000000
0<
#805000000000000
b11 H
b11 B
0?
18
1@
17
1=
b10111100 E
b10111100 K
19
1<
#810000000000000
0<
#815000000000000
09
1<
#820000000000000
0<
#825000000000000
b1111001 K
b1111001 E
0=
07
19
1<
#830000000000000
0<
#835000000000000
09
1<
#840000000000000
0<
#845000000000000
0@
17
1=
b11110010 E
b11110010 K
19
1<
#850000000000000
0<
#855000000000000
09
1<
#860000000000000
0<
#865000000000000
b11100101 K
b11100101 E
0=
19
1<
#870000000000000
0<
#875000000000000
09
1<
#880000000000000
0<
#885000000000000
08
1@
1=
b11001011 E
b11001011 K
19
1<
#890000000000000
0<
#895000000000000
09
1<
#900000000000000
0<
#905000000000000
b10010111 K
b10010111 E
0=
19
1<
#910000000000000
0<
#915000000000000
09
1<
#920000000000000
0<
#925000000000000
0@
07
1=
b101111 E
b101111 K
19
1<
#930000000000000
0<
#935000000000000
09
1<
#940000000000000
0<
#945000000000000
b1011110 K
b1011110 E
0=
19
1<
#950000000000000
0<
#955000000000000
09
1<
#960000000000000
0<
#965000000000000
0>
1C
1I
1?
b100 B
b100 H
18
1@
17
1=
b10111100 E
b10111100 K
19
1<
#970000000000000
0<
#975000000000000
09
1<
#980000000000000
0<
#985000000000000
b1111001 K
b1111001 E
0=
07
19
1<
#990000000000000
0<
#995000000000000
09
1<
#1000000000000000
0<
#1005000000000000
0@
17
1=
b11110010 E
b11110010 K
19
1<
#1010000000000000
0<
#1015000000000000
09
1<
#1020000000000000
0<
#1025000000000000
b11100101 K
b11100101 E
0=
19
1<
#1030000000000000
0<
#1035000000000000
09
1<
#1040000000000000
0<
#1045000000000000
08
1@
1=
b11001011 E
b11001011 K
19
1<
#1050000000000000
0<
#1055000000000000
09
1<
#1060000000000000
0<
#1065000000000000
b10010111 K
b10010111 E
0=
19
1<
#1070000000000000
0<
#1075000000000000
09
1<
#1080000000000000
0<
#1085000000000000
0@
07
1=
b101111 E
b101111 K
19
1<
#1090000000000000
0<
#1095000000000000
09
1<
#1100000000000000
0<
#1105000000000000
b1011110 K
b1011110 E
0=
19
1<
#1110000000000000
0<
#1115000000000000
09
1<
#1120000000000000
0<
#1125000000000000
0?
18
1@
17
1=
b10111100 E
b10111100 K
19
1<
#1130000000000000
0<
#1135000000000000
09
1<
#1140000000000000
0<
#1145000000000000
b1111001 K
b1111001 E
0=
19
1<
#1150000000000000
0<
#1155000000000000
09
1<
#1160000000000000
0<
#1165000000000000
0@
1=
b11110011 E
b11110011 K
19
1<
#1170000000000000
0<
#1175000000000000
09
1<
#1180000000000000
0<
#1185000000000000
b11100111 K
b11100111 E
0=
19
1<
#1190000000000000
0<
#1195000000000000
09
1<
#1200000000000000
0<
#1205000000000000
08
1@
1=
b11001111 E
b11001111 K
19
1<
#1210000000000000
0<
#1215000000000000
09
1<
#1220000000000000
0<
#1225000000000000
b10011111 K
b10011111 E
0=
19
1<
#1230000000000000
0<
#1235000000000000
09
1<
#1240000000000000
0<
#1245000000000000
0@
1=
b111111 E
b111111 K
19
1<
#1250000000000000
0<
#1255000000000000
09
1<
#1260000000000000
0<
#1265000000000000
b1111111 K
b1111111 E
0=
19
1<
#1270000000000000
0<
#1275000000000000
09
1<
#1280000000000000
0<
#1285000000000000
1>
1?
1F
b11111111 6
b11111111 ;
b11111111 D
13
1L
b11111111 5
b11111111 :
b11111111 J
1G
1M
18
1@
1=
b11111111 E
b11111111 K
19
1<
#1290000000000000
0<
#1295000000000000
09
1<
#1300000000000000
0<
#1305000000000000
0=
19
1<
#1310000000000000
0<
#1315000000000000
09
1<
#1320000000000000
0<
#1325000000000000
0@
07
1=
19
1<
#1330000000000000
0<
#1335000000000000
09
1<
#1340000000000000
0<
#1345000000000000
b11111110 K
b11111110 E
0=
17
19
1<
#1350000000000000
0<
#1355000000000000
09
1<
#1360000000000000
0<
#1365000000000000
08
1@
1=
b11111101 E
b11111101 K
19
1<
#1370000000000000
0<
#1375000000000000
09
1<
#1380000000000000
0<
#1385000000000000
b11111011 K
b11111011 E
0=
19
1<
#1390000000000000
0<
#1395000000000000
09
1<
#1400000000000000
0<
#1405000000000000
0@
07
1=
b11110111 E
b11110111 K
19
1<
#1410000000000000
0<
#1415000000000000
09
1<
#1420000000000000
0<
#1425000000000000
b11101110 K
b11101110 E
0=
17
19
1<
#1430000000000000
0<
#1435000000000000
09
1<
#1440000000000000
0<
#1445000000000000
b11011101 5
b11011101 :
b11011101 J
b11011101 6
b11011101 ;
b11011101 D
0?
18
1@
1=
b11011101 E
b11011101 K
19
1<
#1450000000000000
0<
#1455000000000000
09
1<
#1460000000000000
0<
#1465000000000000
b10111011 K
b10111011 E
0=
19
1<
#1470000000000000
0<
#1475000000000000
09
1<
#1480000000000000
0<
#1485000000000000
0@
1=
b1110111 E
b1110111 K
19
1<
#1490000000000000
0<
#1495000000000000
09
1<
#1500000000000000
0<
#1505000000000000
b11101111 K
b11101111 E
0=
07
19
1<
#1510000000000000
0<
#1515000000000000
09
1<
#1520000000000000
0<
#1525000000000000
08
1@
17
1=
b11011110 E
b11011110 K
19
1<
#1530000000000000
0<
#1535000000000000
09
1<
#1540000000000000
0<
#1545000000000000
b10111101 K
b10111101 E
0=
19
1<
#1550000000000000
0<
#1555000000000000
09
1<
#1560000000000000
0<
#1565000000000000
0@
1=
b1111011 E
b1111011 K
19
1<
#1570000000000000
0<
#1575000000000000
09
1<
#1580000000000000
0<
#1585000000000000
b11110111 K
b11110111 E
0=
07
19
1<
#1590000000000000
0<
#1595000000000000
09
1<
#1600000000000000
0<
#1605000000000000
0>
1?
b11101110 6
b11101110 ;
b11101110 D
b11101110 5
b11101110 :
b11101110 J
18
1@
17
1=
b11101110 E
b11101110 K
19
1<
#1610000000000000
0<
#1615000000000000
09
1<
#1620000000000000
0<
#1625000000000000
b11011101 K
b11011101 E
0=
19
1<
#1630000000000000
0<
#1635000000000000
09
1<
#1640000000000000
0<
#1645000000000000
0@
07
1=
b10111011 E
b10111011 K
19
1<
#1650000000000000
0<
#1655000000000000
09
1<
#1660000000000000
0<
#1665000000000000
b1110110 K
b1110110 E
0=
19
1<
#1670000000000000
0<
#1675000000000000
09
1<
#1680000000000000
0<
#1685000000000000
08
1@
17
1=
b11101100 E
b11101100 K
19
1<
#1690000000000000
0<
#1695000000000000
09
1<
#1700000000000000
0<
#1705000000000000
b11011001 K
b11011001 E
0=
19
1<
#1710000000000000
0<
#1715000000000000
09
1<
#1720000000000000
0<
#1725000000000000
0@
07
1=
b10110011 E
b10110011 K
19
1<
#1730000000000000
0<
#1735000000000000
09
1<
#1740000000000000
0<
#1745000000000000
b1100110 K
b1100110 E
0=
19
1<
#1750000000000000
0<
#1755000000000000
09
1<
#1760000000000000
0<
#1765000000000000
b11001100 5
b11001100 :
b11001100 J
b11001100 6
b11001100 ;
b11001100 D
0?
18
1@
17
1=
b11001100 E
b11001100 K
19
1<
#1770000000000000
0<
#1775000000000000
09
1<
#1780000000000000
0<
#1785000000000000
b10011001 K
b10011001 E
0=
07
19
1<
#1790000000000000
0<
#1795000000000000
09
1<
#1800000000000000
0<
#1805000000000000
0@
17
1=
b110010 E
b110010 K
19
1<
#1810000000000000
0<
#1815000000000000
09
1<
#1820000000000000
0<
#1825000000000000
b1100101 K
b1100101 E
0=
19
1<
#1830000000000000
0<
#1835000000000000
09
1<
#1840000000000000
0<
#1845000000000000
08
1@
1=
b11001011 E
b11001011 K
19
1<
#1850000000000000
0<
#1855000000000000
09
1<
#1860000000000000
0<
#1865000000000000
b10010111 K
b10010111 E
0=
07
19
1<
#1870000000000000
0<
#1875000000000000
09
1<
#1880000000000000
0<
#1885000000000000
0@
17
1=
b101110 E
b101110 K
19
1<
#1890000000000000
0<
#1895000000000000
09
1<
#1900000000000000
0<
#1905000000000000
b1011101 K
b1011101 E
0=
19
1<
#1910000000000000
0<
#1915000000000000
09
1<
#1920000000000000
0<
#1925000000000000
1>
1?
b10111011 6
b10111011 ;
b10111011 D
b10111011 5
b10111011 :
b10111011 J
18
1@
1=
b10111011 E
b10111011 K
19
1<
#1930000000000000
0<
#1935000000000000
09
1<
#1940000000000000
0<
#1945000000000000
b1110111 K
b1110111 E
0=
07
19
1<
#1950000000000000
0<
#1955000000000000
09
1<
#1960000000000000
0<
#1965000000000000
0@
1=
b11101110 E
b11101110 K
19
1<
#1970000000000000
0<
#1975000000000000
09
1<
#1980000000000000
0<
#1985000000000000
b11011100 K
b11011100 E
0=
17
19
1<
#1990000000000000
0<
#1995000000000000
09
1<
#2000000000000000
0<
#2005000000000000
08
1@
1=
b10111001 E
b10111001 K
19
1<
#2010000000000000
0<
#2015000000000000
09
1<
#2020000000000000
0<
#2025000000000000
b1110011 K
b1110011 E
0=
07
19
1<
#2030000000000000
0<
#2035000000000000
09
1<
#2040000000000000
0<
#2045000000000000
0@
1=
b11100110 E
b11100110 K
19
1<
#2050000000000000
0<
#2055000000000000
09
1<
#2060000000000000
0<
#2065000000000000
b11001100 K
b11001100 E
0=
17
19
1<
#2070000000000000
0<
#2075000000000000
09
1<
#2080000000000000
0<
#2085000000000000
b10011001 5
b10011001 :
b10011001 J
b10011001 6
b10011001 ;
b10011001 D
0?
18
1@
1=
b10011001 E
b10011001 K
19
1<
#2090000000000000
0<
#2095000000000000
09
1<
#2100000000000000
0<
#2105000000000000
b110011 K
b110011 E
0=
07
19
1<
#2110000000000000
0<
#2115000000000000
09
1<
#2120000000000000
0<
#2125000000000000
0@
17
1=
b1100110 E
b1100110 K
19
1<
#2130000000000000
0<
#2135000000000000
09
1<
#2140000000000000
0<
#2145000000000000
b11001101 K
b11001101 E
0=
07
19
1<
#2150000000000000
0<
#2155000000000000
09
1<
#2160000000000000
0<
#2165000000000000
08
1@
17
1=
b10011010 E
b10011010 K
19
1<
#2170000000000000
0<
#2175000000000000
09
1<
#2180000000000000
0<
#2185000000000000
b110101 K
b110101 E
0=
07
19
1<
#2190000000000000
0<
#2195000000000000
09
1<
#2200000000000000
0<
#2205000000000000
0@
17
1=
b1101010 E
b1101010 K
19
1<
#2210000000000000
0<
#2215000000000000
09
1<
#2220000000000000
0<
#2225000000000000
b11010101 K
b11010101 E
0=
07
19
1<
#2230000000000000
0<
#2235000000000000
09
1<
#2240000000000000
0<
#2245000000000000
0>
1?
b10101010 6
b10101010 ;
b10101010 D
b10101010 5
b10101010 :
b10101010 J
18
1@
17
1=
b10101010 E
b10101010 K
19
1<
#2250000000000000
0<
#2255000000000000
09
1<
#2260000000000000
0<
#2265000000000000
b1010101 K
b1010101 E
0=
07
19
1<
#2270000000000000
0<
#2275000000000000
09
1<
#2280000000000000
0<
#2285000000000000
0@
1=
b10101010 E
b10101010 K
19
1<
#2290000000000000
0<
#2295000000000000
09
1<
#2300000000000000
0<
#2305000000000000
b1010100 K
b1010100 E
0=
19
1<
#2310000000000000
0<
#2315000000000000
09
1<
#2320000000000000
0<
#2325000000000000
08
1@
17
1=
b10101000 E
b10101000 K
19
1<
#2330000000000000
0<
#2335000000000000
09
1<
#2340000000000000
0<
#2345000000000000
b1010001 K
b1010001 E
0=
07
19
1<
#2350000000000000
0<
#2355000000000000
09
1<
#2360000000000000
0<
#2365000000000000
0@
1=
b10100010 E
b10100010 K
19
1<
#2370000000000000
0<
#2375000000000000
09
1<
#2380000000000000
0<
#2385000000000000
b1000100 K
b1000100 E
0=
19
1<
#2390000000000000
0<
#2395000000000000
09
1<
#2400000000000000
0<
#2405000000000000
b10001000 5
b10001000 :
b10001000 J
b10001000 6
b10001000 ;
b10001000 D
0?
18
1@
1=
b10001000 E
b10001000 K
19
1<
#2410000000000000
0<
#2415000000000000
09
1<
#2420000000000000
0<
#2425000000000000
b10000 K
b10000 E
0=
19
1<
#2430000000000000
0<
#2435000000000000
09
1<
#2440000000000000
0<
#2445000000000000
0@
1=
b100000 E
b100000 K
19
1<
#2450000000000000
0<
#2455000000000000
09
1<
#2460000000000000
0<
#2465000000000000
b1000000 K
b1000000 E
0=
19
1<
#2470000000000000
0<
#2475000000000000
09
1<
#2480000000000000
0<
#2485000000000000
08
1@
1=
b10000000 E
b10000000 K
19
1<
#2490000000000000
0<
#2495000000000000
09
1<
#2500000000000000
0<
#2505000000000000
b0 K
b0 E
0=
19
1<
