Paraleloserie/IDLE-COM/tester.v
// Michelle Gutiérrez 
// Cicuitos Digitales 2 - Proyecto1
// Tester paralelltoserial_IDLE



module t_ptos_idle (
   
  
output reg active,
output reg reset,
output reg clk32f,
input wire outc,
input wire outs

);
reg clk4f, clk8f, clk16f, clk;


initial begin
		$dumpfile("ptos_IDLE.vcd");	
		$dumpvars;						
	    	
		active <= 0;

		repeat (8) begin			// checking reset
		@(posedge clk4f);
		#4 reset <= 0; 
		end
		
		@(posedge clk4f);
		#10 reset <= 1;

		repeat (4) begin			// insert BC 10111100 x4 because Valid = 0	
       		 @(posedge clk4f);	
			active <= 1;
		end
	
		@(posedge clk4f);	
		    	active <= 0;
	

        	repeat (4) begin			// 1110 1110
		@(posedge clk4f);	
		    active <= 1;
	
		end
    
		$finish;		
	end

// clks 

	initial clk32f <= 0;
    initial clk16f <= 0;
    initial clk8f <= 0;
    initial clk4f <= 0;
    


    // Faster frequency
    always @(posedge clk) begin
		clk32f <= ~clk32f; // if was LOW change to HIGH
        end 
    //////////////////////////////
    // For 16 Hz
    always @(posedge clk32f) begin
        clk16f <= ~clk16f; // if was LOW change to HIGH
        end
    //////////////////////////////
    // For 8 Hz
    always @(posedge clk16f) begin
            clk8f <= ~clk8f; // if was LOW change to HIGH
    end
    //////////////////////////////
    // For 4 Hz
    always @(posedge clk8f) begin
        clk4f <= ~clk4f; // if was LOW change to HIGH
        end
   

  
	 // clock logic
	
	initial	clk	 				<= 0;			// Initial value to avoid indeterminations
	always	#5 	clk			<= ~clk;		// toggle every 2ns
	

endmodule

Paraleloserie/IDLE-COM/paralelltoserial_IDLE_struct.v
/* Generated by Yosys 0.9 (git sha1 UNKNOWN, gcc 7.5.0-3ubuntu1~18.04 -fPIC -Os) */

(* top =  1  *)
(* src = "paralelltoserial_IDLE.v:7" *)
module paralelo_a_serial_IDLE_struct(active, reset, clk32f, out);
  (* src = "paralelltoserial_IDLE.v:28" *)
  wire _00_;
  (* src = "paralelltoserial_IDLE.v:28" *)
  wire [2:0] _01_;
  (* src = "paralelltoserial_IDLE.v:36" *)
  (* unused_bits = "3" *)
  wire [31:0] _02_;
  wire _03_;
  wire _04_;
  wire _05_;
  wire _06_;
  wire [2:0] _07_;
  wire [1:0] _08_;
  wire [2:0] _09_;
  wire [1:0] _10_;
  wire _11_;
  wire [2:0] _12_;
  wire [2:0] _13_;
  wire _14_;
  wire _15_;
  wire _16_;
  wire _17_;
  wire _18_;
  wire _19_;
  (* src = "paralelltoserial_IDLE.v:44|paralelltoserial_IDLE.v:37|<techmap.v>:432" *)
  wire [6:0] _20_;
  (* src = "paralelltoserial_IDLE.v:44|paralelltoserial_IDLE.v:37|<techmap.v>:428" *)
  wire _21_;
  wire _22_;
  wire _23_;
  wire _24_;
  wire _25_;
  (* src = "paralelltoserial_IDLE.v:36|<techmap.v>:260|<techmap.v>:203" *)
  (* unused_bits = "2" *)
  wire [31:0] _26_;
  (* src = "paralelltoserial_IDLE.v:44|paralelltoserial_IDLE.v:37|<techmap.v>:445" *)
  wire _27_;
  (* src = "paralelltoserial_IDLE.v:9" *)
  input active;
  (* src = "paralelltoserial_IDLE.v:11" *)
  input clk32f;
  (* src = "paralelltoserial_IDLE.v:17" *)
  wire idle0;
  (* src = "paralelltoserial_IDLE.v:17" *)
  wire idle1;
  (* src = "paralelltoserial_IDLE.v:17" *)
  wire idle2;
  (* src = "paralelltoserial_IDLE.v:17" *)
  wire idle3;
  (* src = "paralelltoserial_IDLE.v:17" *)
  wire idle4;
  (* src = "paralelltoserial_IDLE.v:17" *)
  wire idle5;
  (* src = "paralelltoserial_IDLE.v:17" *)
  wire idle6;
  (* src = "paralelltoserial_IDLE.v:17" *)
  wire idle7;
  (* src = "paralelltoserial_IDLE.v:12" *)
  output out;
  (* src = "paralelltoserial_IDLE.v:10" *)
  input reset;
  (* src = "paralelltoserial_IDLE.v:18" *)
  wire [2:0] selector;
  assign _14_ = _03_ |(* src = "paralelltoserial_IDLE.v:43|paralelltoserial_IDLE.v:37" *)  _12_[2];
  assign _15_ = _04_ |(* src = "paralelltoserial_IDLE.v:42|paralelltoserial_IDLE.v:37" *)  _12_[2];
  assign _05_ = _02_[0] |(* src = "paralelltoserial_IDLE.v:41|paralelltoserial_IDLE.v:37" *)  _13_[1];
  assign _16_ = _05_ |(* src = "paralelltoserial_IDLE.v:41|paralelltoserial_IDLE.v:37" *)  selector[2];
  assign _17_ = _06_ |(* src = "paralelltoserial_IDLE.v:40|paralelltoserial_IDLE.v:37" *)  selector[2];
  assign _03_ = _02_[0] |(* src = "paralelltoserial_IDLE.v:39|paralelltoserial_IDLE.v:37" *)  selector[1];
  assign _18_ = _03_ |(* src = "paralelltoserial_IDLE.v:39|paralelltoserial_IDLE.v:37" *)  selector[2];
  assign _07_[2] = _20_[4] |(* src = "paralelltoserial_IDLE.v:44|paralelltoserial_IDLE.v:37|<techmap.v>:441" *)  _20_[5];
  assign _08_[0] = _07_[0] |(* src = "paralelltoserial_IDLE.v:44|paralelltoserial_IDLE.v:37|<techmap.v>:441" *)  _07_[1];
  assign _08_[1] = _07_[2] |(* src = "paralelltoserial_IDLE.v:44|paralelltoserial_IDLE.v:37|<techmap.v>:441" *)  _20_[6];
  assign _21_ = _08_[0] |(* src = "paralelltoserial_IDLE.v:44|paralelltoserial_IDLE.v:37|<techmap.v>:441" *)  _08_[1];
  assign _09_[0] = _23_ |(* src = "paralelltoserial_IDLE.v:44|paralelltoserial_IDLE.v:37|<techmap.v>:445" *)  _07_[0];
  assign _07_[1] = _20_[2] |(* src = "paralelltoserial_IDLE.v:44|paralelltoserial_IDLE.v:37|<techmap.v>:445" *)  _20_[3];
  assign _09_[2] = _20_[4] |(* src = "paralelltoserial_IDLE.v:44|paralelltoserial_IDLE.v:37|<techmap.v>:445" *)  _24_;
  assign _10_[0] = _09_[0] |(* src = "paralelltoserial_IDLE.v:44|paralelltoserial_IDLE.v:37|<techmap.v>:445" *)  _07_[1];
  assign _10_[1] = _09_[2] |(* src = "paralelltoserial_IDLE.v:44|paralelltoserial_IDLE.v:37|<techmap.v>:445" *)  _25_;
  assign _27_ = _10_[0] |(* src = "paralelltoserial_IDLE.v:44|paralelltoserial_IDLE.v:37|<techmap.v>:445" *)  _10_[1];
  assign _06_ = selector[0] |(* src = "paralelltoserial_IDLE.v:44|paralelltoserial_IDLE.v:37" *)  _13_[1];
  assign _19_ = _06_ |(* src = "paralelltoserial_IDLE.v:44|paralelltoserial_IDLE.v:37" *)  _12_[2];
  assign _04_ = selector[0] |(* src = "paralelltoserial_IDLE.v:38|paralelltoserial_IDLE.v:37" *)  selector[1];
  assign _11_ = _04_ |(* src = "paralelltoserial_IDLE.v:38|paralelltoserial_IDLE.v:37" *)  selector[2];
  assign _07_[0] = ~(* src = "paralelltoserial_IDLE.v:43|paralelltoserial_IDLE.v:37" *) _14_;
  assign _20_[2] = ~(* src = "paralelltoserial_IDLE.v:42|paralelltoserial_IDLE.v:37" *) _15_;
  assign _20_[3] = ~(* src = "paralelltoserial_IDLE.v:41|paralelltoserial_IDLE.v:37" *) _16_;
  assign _20_[4] = ~(* src = "paralelltoserial_IDLE.v:40|paralelltoserial_IDLE.v:37" *) _17_;
  assign _24_ = ~(* src = "paralelltoserial_IDLE.v:39|paralelltoserial_IDLE.v:37" *) _18_;
  assign _25_ = ~(* src = "paralelltoserial_IDLE.v:38|paralelltoserial_IDLE.v:37" *) _11_;
  assign _23_ = ~(* src = "paralelltoserial_IDLE.v:44|paralelltoserial_IDLE.v:37" *) _19_;
  assign _00_ = reset ? (* src = "paralelltoserial_IDLE.v:29" *) _22_ : 1'h0;
  assign idle0 = ~(* src = "paralelltoserial_IDLE.v:22" *) active;
  assign _22_ = _27_ ? (* src = "paralelltoserial_IDLE.v:44|paralelltoserial_IDLE.v:37|<techmap.v>:445" *) _21_ : 1'h0;
  assign _01_[0] = reset ? (* src = "paralelltoserial_IDLE.v:29" *) _02_[0] : 1'h1;
  assign _01_[1] = reset ? (* src = "paralelltoserial_IDLE.v:29" *) _02_[1] : 1'h1;
  assign _01_[2] = reset ? (* src = "paralelltoserial_IDLE.v:29" *) _02_[2] : 1'h1;
  (* src = "paralelltoserial_IDLE.v:28" *)
  DFF _62_ (
    .C(clk32f),
    .D(_00_),
    .Q(out)
  );
  (* src = "paralelltoserial_IDLE.v:28" *)
  DFF _63_ (
    .C(clk32f),
    .D(_01_[0]),
    .Q(selector[0])
  );
  (* src = "paralelltoserial_IDLE.v:28" *)
  DFF _64_ (
    .C(clk32f),
    .D(_01_[1]),
    .Q(selector[1])
  );
  (* src = "paralelltoserial_IDLE.v:28" *)
  DFF _65_ (
    .C(clk32f),
    .D(_01_[2]),
    .Q(selector[2])
  );
  assign _12_[2] = selector[2] ^(* src = "paralelltoserial_IDLE.v:42|paralelltoserial_IDLE.v:37" *)  1'h1;
  assign _13_[1] = selector[1] ^(* src = "paralelltoserial_IDLE.v:40|paralelltoserial_IDLE.v:37" *)  1'h1;
  assign _02_[0] = selector[0] ^(* src = "paralelltoserial_IDLE.v:39|paralelltoserial_IDLE.v:37" *)  1'h1;
  assign _20_[6] = idle0 &(* src = "paralelltoserial_IDLE.v:44|paralelltoserial_IDLE.v:37|<techmap.v>:434" *)  _25_;
  assign _20_[5] = active &(* src = "paralelltoserial_IDLE.v:44|paralelltoserial_IDLE.v:37|<techmap.v>:434" *)  _24_;
  assign _02_[1] = selector[1] ^(* src = "paralelltoserial_IDLE.v:36|<techmap.v>:263" *)  selector[0];
  assign _02_[2] = selector[2] ^(* src = "paralelltoserial_IDLE.v:36|<techmap.v>:263" *)  _26_[1];
  assign _26_[1] = selector[1] &(* src = "paralelltoserial_IDLE.v:36|<techmap.v>:260|<techmap.v>:221" *)  selector[0];
  assign _02_[31:4] = 28'h0000000;
  assign _09_[1] = _07_[1];
  assign _12_[1:0] = selector[1:0];
  assign { _13_[2], _13_[0] } = { selector[2], _02_[0] };
  assign _20_[1:0] = { _07_[0], 1'h0 };
  assign { _26_[31:2], _26_[0] } = { 29'h00000000, _02_[3], selector[0] };
  assign idle1 = active;
  assign idle2 = 1'h1;
  assign idle3 = 1'h1;
  assign idle4 = 1'h1;
  assign idle5 = 1'h1;
  assign idle6 = 1'h0;
  assign idle7 = 1'h0;
endmodule

Paraleloserie/IDLE-COM/paralelltoserial_IDLE.v
// Michelle Gutiérrez 
// Cicuitos Digitales 2 - Proyecto1
// Paralelltoserial con IDLE

// Dependiendo del valor de la señal de active, envia de forma serial 7C O BC

module paralelo_a_serial_IDLE(

input wire active,
input wire reset,
input wire clk32f,
output reg out  
);



reg idle0, idle1, idle2, idle3, idle4, idle5, idle6, idle7;
reg [2:0] selector;

// Si el dato es valido se llenan los paquetes de bits y sino se pasa BC
 always @ (*)
        if(active == 1)
        {idle0, idle1, idle2, idle3, idle4, idle5, idle6, idle7} = 'h7C;
        else begin
        {idle0, idle1, idle2, idle3, idle4, idle5, idle6, idle7} = 'hBC;
        end

always @(posedge clk32f)begin
        if (reset == 0) 
        begin
        out <= 0;
        selector <= 3'b111;
        end
        else begin 
        // Lógica para cuando reset == 1
        selector <= selector + 1;
        case ({selector})
        3'b000: out <= idle0;
        3'b001: out <= idle1;
        3'b010: out <= idle2;
        3'b011: out <= idle3;
        3'b100: out <= idle4;
        3'b101: out <= idle5;
        3'b110: out <= idle6;
        default: out <= idle7;

        endcase
    end
end

endmodule

testbenches/tb_ptos_idle.v
`timescale 	1ns/1ps

`include "paralelltoserial_IDLE.v"
`include "tester.v"
`include "paralelltoserial_IDLE_struct.v"
`include "cmos_cells.v"

module testbench_ptos_idle;


 wire active;
 wire reset;
 wire clk4f;
 wire clk32f;
 wire outc;
 wire outs;

paralelo_a_serial_IDLE paralelo_a_serialtb_b(
                                        .active  (active),
                                        .reset (reset),
                                        .clk32f (clk32f),
                                        .out    (outc)
);


paralelo_a_serial_IDLE_struct paralelo_a_serialtb_s(
                                        .active  (active),
                                        .reset (reset),
                                        .clk32f (clk32f),
                                        .out    (outs)
);




t_ptos_idle t_ptostb(      
                      .active (active),
                      .reset (reset),
                      .clk32f (clk32f),
                      .outc    (outc),
                      .outs    (outs)
);

endmodule

Paraleloserie/Paraleloserie/cmos_cells.v
module BUF(A, Y);
input A;
output Y;
assign  Y = A;
endmodule

module NOT(A, Y);
input A;
output Y;
assign   Y = ~A;
endmodule

module NAND(A, B, Y);
input A, B;
output Y;
assign   Y = ~(A & B);
endmodule

module NOR(A, B, Y);
input A, B;
output Y;
assign   Y = ~(A | B);
endmodule

module DFF(C, D, Q);
input C, D;
output reg Q;
always @(posedge C)
	Q <= D;
endmodule

module DFFSR(C, D, Q, S, R);
input C, D, S, R;
output reg Q;
always @(posedge C, posedge S, posedge R)

	if (S)
		Q <= 1'b1;
	else if (R)
		Q <= 1'b0;
	else
		Q <= D;
endmodule

Paraleloserie/IDLE-COM/ptos_IDLE.vcd
$date
	Fri Jun  5 20:39:24 2020
$end
$version
	Icarus Verilog
$end
$timescale
	1ps
$end
$scope module BUF $end
$var wire 1 ! A $end
$var wire 1 " Y $end
$upscope $end
$scope module DFFSR $end
$var wire 1 # C $end
$var wire 1 $ D $end
$var wire 1 % R $end
$var wire 1 & S $end
$var reg 1 ' Q $end
$upscope $end
$scope module NAND $end
$var wire 1 ( A $end
$var wire 1 ) B $end
$var wire 1 * Y $end
$upscope $end
$scope module NOR $end
$var wire 1 + A $end
$var wire 1 , B $end
$var wire 1 - Y $end
$upscope $end
$scope module NOT $end
$var wire 1 . A $end
$var wire 1 / Y $end
$upscope $end
$scope module testbench_ptos_idle $end
$var wire 1 0 reset $end
$var wire 1 1 outs $end
$var wire 1 2 outc $end
$var wire 1 3 clk32f $end
$var wire 1 4 active $end
$scope module paralelo_a_serialtb_b $end
$var wire 1 0 reset $end
$var wire 1 3 clk32f $end
$var wire 1 4 active $end
$var reg 1 5 idle0 $end
$var reg 1 6 idle1 $end
$var reg 1 7 idle2 $end
$var reg 1 8 idle3 $end
$var reg 1 9 idle4 $end
$var reg 1 : idle5 $end
$var reg 1 ; idle6 $end
$var reg 1 < idle7 $end
$var reg 1 2 out $end
$var reg 3 = selector [2:0] $end
$upscope $end
$scope module paralelo_a_serialtb_s $end
$var wire 1 > _03_ $end
$var wire 1 ? _04_ $end
$var wire 1 @ _05_ $end
$var wire 1 A _06_ $end
$var wire 1 B _11_ $end
$var wire 1 C _14_ $end
$var wire 1 D _15_ $end
$var wire 1 E _16_ $end
$var wire 1 F _17_ $end
$var wire 1 G _18_ $end
$var wire 1 H _19_ $end
$var wire 1 I _21_ $end
$var wire 1 J _23_ $end
$var wire 1 K _24_ $end
$var wire 1 L _25_ $end
$var wire 1 M _27_ $end
$var wire 1 N idle0 $end
$var wire 1 O idle1 $end
$var wire 1 P idle2 $end
$var wire 1 Q idle3 $end
$var wire 1 R idle4 $end
$var wire 1 S idle5 $end
$var wire 1 T idle6 $end
$var wire 1 U idle7 $end
$var wire 3 V selector [2:0] $end
$var wire 1 0 reset $end
$var wire 1 1 out $end
$var wire 1 3 clk32f $end
$var wire 1 4 active $end
$var wire 32 W _26_ [31:0] $end
$var wire 1 X _22_ $end
$var wire 7 Y _20_ [6:0] $end
$var wire 3 Z _13_ [2:0] $end
$var wire 3 [ _12_ [2:0] $end
$var wire 2 \ _10_ [1:0] $end
$var wire 3 ] _09_ [2:0] $end
$var wire 2 ^ _08_ [1:0] $end
$var wire 3 _ _07_ [2:0] $end
$var wire 32 ` _02_ [31:0] $end
$var wire 3 a _01_ [2:0] $end
$var wire 1 b _00_ $end
$scope module _62_ $end
$var wire 1 b D $end
$var wire 1 3 C $end
$var reg 1 1 Q $end
$upscope $end
$scope module _63_ $end
$var wire 1 c D $end
$var wire 1 3 C $end
$var reg 1 d Q $end
$upscope $end
$scope module _64_ $end
$var wire 1 e D $end
$var wire 1 3 C $end
$var reg 1 f Q $end
$upscope $end
$scope module _65_ $end
$var wire 1 g D $end
$var wire 1 3 C $end
$var reg 1 h Q $end
$upscope $end
$upscope $end
$scope module t_ptostb $end
$var wire 1 2 outc $end
$var wire 1 1 outs $end
$var reg 1 4 active $end
$var reg 1 i clk $end
$var reg 1 j clk16f $end
$var reg 1 3 clk32f $end
$var reg 1 k clk4f $end
$var reg 1 l clk8f $end
$var reg 1 0 reset $end
$upscope $end
$upscope $end
$enddefinitions $end
#0
$dumpvars
0l
0k
0j
0i
xh
xg
xf
xe
xd
xc
xb
bx a
b0zxxx `
bx _
bx ^
bx ]
bx \
bx [
bx Z
bx0xxxx0 Y
xX
b0zxx W
bx V
0U
0T
1S
1R
1Q
1P
0O
1N
xM
xL
xK
xJ
xI
xH
xG
xF
xE
xD
xC
xB
xA
x@
x?
x>
bx =
0<
0;
1:
19
18
17
06
15
04
03
x2
x1
x0
z/
z.
x-
z,
z+
x*
z)
z(
x'
z&
z%
z$
z#
z"
z!
$end
#5000
1k
1l
02
1j
13
1i
#9000
1g
1e
1c
b111 a
0b
00
#10000
0i
#15000
03
1i
#20000
0i
#25000
0X
0I
0M
b0 ^
b0 \
b0 ]
b0 _
0@
0J
0L
0K
b0 Y
1C
1D
1H
1B
1G
1F
1E
b100 Z
1>
b0z000 `
b0z11 W
1?
1A
b11 [
0j
1h
1f
b111 V
1d
01
b111 =
13
1i
#30000
0i
#35000
03
1i
#40000
0i
#45000
0l
1j
13
1i
#50000
0i
#55000
03
1i
#60000
0i
#65000
0j
13
1i
#70000
0i
#75000
03
1i
#80000
0i
#85000
0k
1l
1j
13
1i
#90000
0i
#95000
03
1i
#100000
0i
#105000
0j
13
1i
#110000
0i
#115000
03
1i
#120000
0i
#125000
0l
1j
13
1i
#130000
0i
#135000
03
1i
#140000
0i
#145000
0j
13
1i
#150000
0i
#155000
03
1i
#160000
0i
#165000
1k
1l
1j
13
1i
#170000
0i
#175000
03
1i
#180000
0i
#185000
0j
13
1i
#190000
0i
#195000
03
1i
#200000
0i
#205000
0l
1j
13
1i
#210000
0i
#215000
03
1i
#220000
0i
#225000
0j
13
1i
#230000
0i
#235000
03
1i
#240000
0i
#245000
0k
1l
1j
13
1i
#250000
0i
#255000
03
1i
#260000
0i
#265000
0j
13
1i
#270000
0i
#275000
03
1i
#280000
0i
#285000
0l
1j
13
1i
#290000
0i
#295000
03
1i
#300000
0i
#305000
0j
13
1i
#310000
0i
#315000
03
1i
#320000
0i
#325000
1k
1l
1j
13
1i
#330000
0i
#335000
03
1i
#340000
0i
#345000
0j
13
1i
#350000
0i
#355000
03
1i
#360000
0i
#365000
0l
1j
13
1i
#370000
0i
#375000
03
1i
#380000
0i
#385000
0j
13
1i
#390000
0i
#395000
03
1i
#400000
0i
#405000
0k
1l
1j
13
1i
#410000
0i
#415000
03
1i
#420000
0i
#425000
0j
13
1i
#430000
0i
#435000
03
1i
#440000
0i
#445000
0l
1j
13
1i
#450000
0i
#455000
03
1i
#460000
0i
#465000
0j
13
1i
#470000
0i
#475000
03
1i
#480000
0i
#485000
1k
1l
1j
13
1i
#490000
0i
#495000
03
1i
#500000
0i
#505000
0j
13
1i
#510000
0i
#515000
03
1i
#520000
0i
#525000
0l
1j
13
1i
#530000
0i
#535000
03
1i
#540000
0i
#545000
0j
13
1i
#550000
0i
#555000
03
1i
#560000
0i
#565000
0k
1l
1j
13
1i
#570000
0i
#575000
03
1i
#580000
0i
#585000
0j
13
1i
#590000
0i
#595000
03
1i
#600000
0i
#605000
0l
1j
13
1i
#610000
0i
#615000
03
1i
#620000
0i
#625000
0j
13
1i
#630000
0i
#635000
03
1i
#640000
0i
#645000
1k
1l
1j
13
1i
#650000
0i
#655000
03
1i
#660000
0i
#665000
0j
13
1i
#670000
0i
#675000
03
1i
#680000
0i
#685000
0l
1j
13
1i
#690000
0i
#695000
03
1i
#700000
0i
#705000
0j
13
1i
#710000
0i
#715000
03
1i
#720000
0i
#725000
0k
1l
1j
13
1i
#730000
0i
#735000
03
1i
#740000
0i
#745000
0j
13
1i
#750000
0i
#755000
03
1i
#760000
0i
#765000
0l
1j
13
1i
#770000
0i
#775000
03
1i
#780000
0i
#785000
0j
13
1i
#790000
0i
#795000
03
1i
#800000
0i
#805000
1k
1l
1j
13
1i
#810000
0i
#815000
03
1i
#820000
0i
#825000
0j
13
1i
#830000
0i
#835000
03
1i
#840000
0i
#845000
0l
1j
13
1i
#850000
0i
#855000
03
1i
#860000
0i
#865000
0j
13
1i
#870000
0i
#875000
03
1i
#880000
0i
#885000
0k
1l
1j
13
1i
#890000
0i
#895000
03
1i
#900000
0i
#905000
0j
13
1i
#910000
0i
#915000
03
1i
#920000
0i
#925000
0l
1j
13
1i
#930000
0i
#935000
03
1i
#940000
0i
#945000
0j
13
1i
#950000
0i
#955000
03
1i
#960000
0i
#965000
1k
1l
1j
13
1i
#970000
0i
#975000
03
1i
#980000
0i
#985000
0j
13
1i
#990000
0i
#995000
03
1i
#1000000
0i
#1005000
0l
1j
13
1i
#1010000
0i
#1015000
03
1i
#1020000
0i
#1025000
0j
13
1i
#1030000
0i
#1035000
03
1i
#1040000
0i
#1045000
0k
1l
1j
13
1i
#1050000
0i
#1055000
03
1i
#1060000
0i
#1065000
0j
13
1i
#1070000
0i
#1075000
03
1i
#1080000
0i
#1085000
0l
1j
13
1i
#1090000
0i
#1095000
03
1i
#1100000
0i
#1105000
0j
13
1i
#1110000
0i
#1115000
03
1i
#1120000
0i
#1125000
1k
1l
1j
13
1i
#1130000
0i
#1135000
03
1i
#1140000
0i
#1145000
0j
13
1i
#1150000
0i
#1155000
03
1i
#1160000
0i
#1165000
0l
1j
13
1i
#1170000
0i
#1175000
03
1i
#1180000
0i
#1185000
0j
13
1i
#1190000
0i
#1195000
03
1i
#1200000
0i
#1205000
0k
1l
1j
13
1i
#1210000
0i
#1215000
03
1i
#1220000
0i
#1225000
0j
13
1i
#1230000
0i
#1235000
03
1i
#1240000
0i
#1245000
0l
1j
13
1i
#1250000
0i
#1255000
03
1i
#1260000
0i
#1265000
0j
13
1i
#1270000
0i
#1275000
03
1i
#1280000
0i
#1285000
1k
1l
1j
13
1i
#1290000
0i
#1295000
03
0g
0e
0c
b0 a
1i
10
#1300000
0i
#1305000
1b
1X
1I
1M
b10 ^
0g
1c
b10 \
b0 ]
b0 _
b1 a
1@
0J
1L
0K
b1000000 Y
1C
1D
1H
0B
1G
1F
1E
b11 Z
1>
b0z001 `
b0z00 W
0?
1A
b100 [
0j
0h
0f
b0 V
0d
b0 =
13
1i
#1310000
0i
#1315000
03
1i
#1320000
0i
#1325000
0l
0I
0b
0X
b100 ]
b0 ^
1M
1K
0c
0G
1e
b0 Y
b10 \
b10 Z
0>
b10 a
0L
1B
b0z010 `
b0z01 W
1?
b101 [
12
b1 =
11
b1 V
1d
1j
13
1i
#1330000
0i
#1335000
03
1i
#1340000
0i
#1345000
1b
1X
1I
b10 ^
1M
b100 _
b10 \
b10000 Y
0F
b100 ]
1c
0A
0K
b11 a
1G
b1 Z
1>
b0z011 `
b0z00 W
b110 [
0j
1f
b10 V
0d
01
02
b10 =
13
1i
#1350000
0i
#1355000
03
1i
#1360000
0i
#1365000
0k
1l
1b
1X
1M
1I
b1 \
b1 ^
1g
b10 ]
b10 _
0c
0E
0e
b0 Z
0@
b100 a
b1000 Y
1F
b0z100 `
b0z11 W
1A
b111 [
12
b11 =
11
b11 V
1d
1j
13
1i
#1370000
0i
#1375000
03
1i
#1380000
0i
#1385000
1b
1X
1M
1I
b1 \
b1 ^
b10 ]
1g
b10 _
1c
0D
b101 a
1@
b100 Y
1E
b111 Z
1>
b0z101 `
b0z00 W
0?
1A
b0 [
0j
1h
0f
b100 V
0d
b100 =
13
1i
#1390000
0i
#1395000
03
1i
#1400000
0i
#1405000
0l
1b
1X
1M
b1 \
b1 ]
b1 _
0c
0C
1e
b110 Z
0>
b110 a
b10 Y
1D
b0z110 `
b0z01 W
1?
b1 [
b101 =
b101 V
1d
1j
13
1i
#1410000
0i
#1415000
03
1i
#1420000
0i
#1425000
1M
0b
0X
b1 \
0I
1J
b1 ]
b0 ^
0H
b0 Y
1c
0A
b0 _
b111 a
1C
b101 Z
1>
b0z111 `
b0z00 W
b10 [
0j
1f
b110 V
0d
b110 =
13
1i
#1430000
0i
#1435000
03
1i
#1440000
0i
#1445000
0N
05
16
1O
14
1k
1l
0M
0g
b0 \
0c
0e
b0 ]
b100 Z
0@
b0 a
0J
1H
b0z000 `
b0z11 W
1A
b11 [
02
b111 =
01
b111 V
1d
1j
13
1i
#1450000
0i
#1455000
03
1i
#1460000
0i
#1465000
0b
0X
0I
1M
b0 ^
0g
1c
b10 \
b0 ]
b0 _
b1 a
1@
0J
1L
0K
b0 Y
1C
1D
1H
0B
1G
1F
1E
b11 Z
1>
b0z001 `
b0z00 W
0?
1A
b100 [
0j
0h
0f
b0 V
0d
b0 =
13
1i
#1470000
0i
#1475000
03
1i
#1480000
0i
#1485000
0l
1b
1X
1I
b10 ^
b100 _
b100000 Y
b100 ]
1M
1K
0c
0G
1e
b10 \
b10 Z
0>
b10 a
0L
1B
b0z010 `
b0z01 W
1?
b101 [
b1 =
b1 V
1d
1j
13
1i
#1490000
0i
#1495000
03
1i
#1500000
0i
#1505000
1I
1b
1X
b10 ^
1M
b100 _
b10 \
0F
b10000 Y
b100 ]
1c
0A
0K
b11 a
1G
b1 Z
1>
b0z011 `
b0z00 W
b110 [
0j
1f
b10 V
0d
11
12
b10 =
13
1i
#1510000
0i
#1515000
03
1i
#1520000
0i
#1525000
0k
1l
1b
1X
1M
1I
b1 \
b1 ^
1g
b10 ]
b10 _
0c
0E
0e
b0 Z
0@
b100 a
b1000 Y
1F
b0z100 `
b0z11 W
1A
b111 [
b11 =
b11 V
1d
1j
13
1i
#1530000
0i
#1535000
03
1i
#1540000
0i
#1545000
1b
1X
1M
1I
b1 \
b1 ^
b10 ]
1g
b10 _
1c
0D
b101 a
1@
b100 Y
1E
b111 Z
1>
b0z101 `
b0z00 W
0?
1A
b0 [
0j
1h
0f
b100 V
0d
b100 =
13
1i
#1550000
0i
#1555000
03
1i
#1560000
0i
#1565000
0l
1b
1X
1M
b1 \
b1 ]
b1 _
0c
0C
1e
b110 Z
0>
b110 a
b10 Y
1D
b0z110 `
b0z01 W
1?
b1 [
b101 =
b101 V
1d
1j
13
1i
#1570000
0i
#1575000
03
1i
#1580000
0i
#1585000
1M
0b
0X
b1 \
0I
1J
b1 ]
b0 ^
0H
b0 Y
1c
0A
b0 _
b111 a
1C
b101 Z
1>
b0z111 `
b0z00 W
b10 [
0j
1f
b110 V
0d
b110 =
13
1i
#1590000
0i
#1595000
03
1i
#1600000
0i
#1605000
1k
1l
0M
0g
b0 \
0c
0e
b0 ]
b100 Z
0@
b0 a
0J
1H
b0z000 `
b0z11 W
1A
b11 [
02
b111 =
01
b111 V
1d
1j
13
1i
#1610000
0i
#1615000
03
1i
#1620000
0i
#1625000
0b
0X
0I
1M
b0 ^
0g
1c
b10 \
b0 ]
b0 _
b1 a
1@
0J
1L
0K
b0 Y
1C
1D
1H
0B
1G
1F
1E
b11 Z
1>
b0z001 `
b0z00 W
0?
1A
b100 [
0j
0h
0f
b0 V
0d
b0 =
13
1i
#1630000
0i
#1635000
03
1i
#1640000
0i
#1645000
0l
1b
1X
1I
b10 ^
b100 _
b100000 Y
b100 ]
1M
1K
0c
0G
1e
b10 \
b10 Z
0>
b10 a
0L
1B
b0z010 `
b0z01 W
1?
b101 [
b1 =
b1 V
1d
1j
13
1i
#1650000
0i
#1655000
03
1i
#1660000
0i
#1665000
1I
1b
1X
b10 ^
1M
b100 _
b10 \
0F
b10000 Y
b100 ]
1c
0A
0K
b11 a
1G
b1 Z
1>
b0z011 `
b0z00 W
b110 [
0j
1f
b10 V
0d
11
12
b10 =
13
1i
#1670000
0i
#1675000
03
1i
#1680000
0i
#1685000
0k
1l
1b
1X
1M
1I
b1 \
b1 ^
1g
b10 ]
b10 _
0c
0E
0e
b0 Z
0@
b100 a
b1000 Y
1F
b0z100 `
b0z11 W
1A
b111 [
b11 =
b11 V
1d
1j
13
1i
#1690000
0i
#1695000
03
1i
#1700000
0i
#1705000
1b
1X
1M
1I
b1 \
b1 ^
b10 ]
1g
b10 _
1c
0D
b101 a
1@
b100 Y
1E
b111 Z
1>
b0z101 `
b0z00 W
0?
1A
b0 [
0j
1h
0f
b100 V
0d
b100 =
13
1i
#1710000
0i
#1715000
03
1i
#1720000
0i
#1725000
0l
1b
1X
1M
b1 \
b1 ]
b1 _
0c
0C
1e
b110 Z
0>
b110 a
b10 Y
1D
b0z110 `
b0z01 W
1?
b1 [
b101 =
b101 V
1d
1j
13
1i
#1730000
0i
#1735000
03
1i
#1740000
0i
#1745000
1M
0b
0X
b1 \
0I
1J
b1 ]
b0 ^
0H
b0 Y
1c
0A
b0 _
b111 a
1C
b101 Z
1>
b0z111 `
b0z00 W
b10 [
0j
1f
b110 V
0d
b110 =
13
1i
#1750000
0i
#1755000
03
1i
#1760000
0i
#1765000
1k
1l
0M
0g
b0 \
0c
0e
b0 ]
b100 Z
0@
b0 a
0J
1H
b0z000 `
b0z11 W
1A
b11 [
02
b111 =
01
b111 V
1d
1j
13
1i
#1770000
0i
#1775000
03
1i
#1780000
0i
#1785000
0b
0X
0I
1M
b0 ^
0g
1c
b10 \
b0 ]
b0 _
b1 a
1@
0J
1L
0K
b0 Y
1C
1D
1H
0B
1G
1F
1E
b11 Z
1>
b0z001 `
b0z00 W
0?
1A
b100 [
0j
0h
0f
b0 V
0d
b0 =
13
1i
#1790000
0i
#1795000
03
1i
#1800000
0i
