MUX4a2/tester.v
`timescale 1ns / 1ps
//////////////////////////////////////////////////////////////////////////////////
// Company: U.C.R E.I.E
// Engineer: Brandon ESquivel Molina
// 
// Create Date: 19.05.2020
// Design Name: mux2x1_8bits+VALID with automatic selector
// Module Name: Tester for mux4x2 8BITS + VALID
// Project Name: PHY Layer PCIe
// Target Devices: PCIe
// Tool Versions: Yosys 0.9 Iverolg release at 2020
// Description: tester for module Mux4x2 8bits+ valid
// Dependencies: mux2x1_behav
// 
// Revision: 0.0
// Revision 0.01 - File Created
// Additional Comments: A conversion of MUX2X1 4bits
// 
//////////////////////////////////////////////////////////////////////////////////


module tester(
	//OUTPUTS
	output reg [8:0] in0,					// datas in with valid at [0] pos
	output reg [8:0] in1,
	output reg [8:0] in2,
	output reg [8:0] in3,
	output reg reset,							// reset in
	output reg clk,							// clock
    //INPUTS
	input wire [8:0] out0,					// data out0
	input wire [8:0] out1					// data out1
 );

reg [3:0] count0;		// posedge Trans counter
reg [3:0] count1;

initial begin
		$dumpfile("muxy.vcd");																						// "dump" file
		$dumpvars;																									// "dumpping" variables
		$display ("clk,\tin0,\tin1,\tin2,\tin3,\tout0,\tout1,\tcount0,\tcount1,\treset");														// print onces
		$monitor($time,"%b\t\t%b\t\t%b\t%b\t%b\t%b\t%b\t%b\t%b\t%b", clk, in0, in1,in2, in3, out0, out1, count0, count1,reset); 							// print everytime	
		repeat (2) begin																							// Repeat the test 3 times
		
		@(posedge clk);																								// sync with clock
		in0 <= 9'b111111110;																					// change the inputs	 	
		reset = 1;				// testing reset

		@(posedge clk);			// testing valid		
		{in1} <= {in1}-1;		// all signal with valid 0, so, memory dt out
		{in0} <= 9'b01010100;
		{in2} <= 9'b01010100;
		{in3} <= 9'b00010000;													
		
		@(posedge clk);			// checking auto select - All signals constant

		{in0} <= 9'b10000001;		// all signal with valid 1, so, out can change
		{in1} <= 9'b01000001;
		{in2} <= 9'b00100001;
		{in3} <= 9'b00010001;	

		@(posedge clk);			// checking auto select - All signals constant 2nd cycle

		{in0} <= 9'b10000001;		// all signal with valid 1, so, out can change
		{in1} <= 9'b01000001;
		{in2} <= 9'b00100001;
		{in3} <= 9'b00010001;	


		@(posedge clk);			// checking auto select - All signals constant 3rd cycle

		{in0} <= 9'b10000001;		// all signal with valid,1, so, out can change
		{in1} <= 9'b01000001;
		{in2} <= 9'b00100001;
		{in3} <= 9'b00010001;	

		@(posedge clk);			// checking auto select - All signals constant 4nd cycle

		{in0} <= 9'b10000001;		// all signal with valid 1, so, out can change
		{in1} <= 9'b01000001;
		{in2} <= 9'b00100001;
		{in3} <= 9'b00010001;	

		end

       	$finish;													// save variables finish
		end															// initial begin
	

	

	// Initial Values - all with valid 1
	initial	in0			<= 9'b011111111;
	initial in1			<= 9'b1;
	initial in2			<= 9'b010101011;
	initial in3			<= 9'b1;	
	initial #2 reset 	<= 0;

	// clock logic
	initial	clk	 		<= 0;			// Initial value to avoid indeterminations
	always	#10 clk 	<= ~clk;		// toggle every 10ns

	// Positive Transitions Counter
	initial count0 <= 0;
	always@(posedge out0) begin
	count0<=count0+1;
	end	

	// Positive Transitions Counter
	initial count1 <= 0;
	always@(posedge out1) begin
	count1<=count1+1;
	end	

endmodule

MUX2a1/mux2x1_behav.v
`timescale 1ns / 1ps
//////////////////////////////////////////////////////////////////////////////////
// Company: U.C.R EIE
// Engineer: Brandon Esquivel Molina
// 
// Create Date: 19.05.2020
// Design Name: mux2x1_8bits+VALID with automatic selector
// Module Name: mux2x1 8BITS + VALID
// Project Name: PHY Layer PCIe
// Target Devices: PCIe
// Tool Versions: Yosys 0.9 Iverolg release at 2020
// Description: module Mux2x1 8bits+ valid a submodule in mux4x2 8bits + valid first level L1
// Dependencies: 
// 
// Revision: 0.0
// Revision 0.01 - File Created
// Additional Comments: A conversion of MUX2X1 4bits
// 
//////////////////////////////////////////////////////////////////////////////////

module mux2x1_behav(                 		// starts behavorial module
    
	//INPUTS
	input wire clk,         				// clock in @f
	input wire [8:0] in0,					// datas in with valid at [0] pos
	input wire [8:0] in1,
	input reset,							// reset in

	//OUTPUTS
	output reg [8:0] out					// data out
 );
    
	//AUXILIARY
	reg selector;
    
    // AUTOMATIC SELECTOR LOGIC
	always @(posedge clk) begin					// triggered at clk or by pressing the reset button
		if(~reset) begin
			selector <= 0;						// reset condition default
        end	else begin
			selector <= ~selector;				// make toggle at posedge clock
        	end
    	end


	// SEQUENTIAL LOGIC START
	always @ (posedge clk) begin         	
		if (~reset) begin
            out <= 0;
		end else begin
			if(selector) begin								// MUX select in1 
				if(in1[0]) begin							// checking valid bit for in1
					out <= in1;								// spreading signal in1
				end else begin
							out <= {out[8:1], in1[0]};		// if valid=0 keep the last dataout, rewriting valid bit, just in case.
						end
			end else begin									// MUX select in0
				if (in0[0]) begin							// checking valid bit for in0
					out <= in0;								// spreading signal in0
				end 
				else begin
					out <= {out[8:1], in0[0]};		// if valid=0 keep the last dataout, rewriting valid bit, just in case.
				end
			end 
		end
	end

endmodule                               // FIN

MUX4a2/mux4x2_behav.v
`timescale 1ns / 1ps
`include "mux2x1_behav.v"
//////////////////////////////////////////////////////////////////////////////////
// Company: U.C.R EIE
// Engineer: Brandon Esquivel Molina
// 
// Create Date: 19.05.2020
// Design Name: mux4x2_8bits+VALID with automatic selector
// Module Name: mux4x2 8BITS + VALID
// Project Name: PHY Layer PCIe
// Target Devices: PCIe
// Tool Versions: Yosys 0.9 Iverolg release at 2020
// Description: module Mux4x2 8bits+ valid with submodule mux2x1 8bits + valid receives four 8-bit+valid inputs and selects two
// Dependencies: mux2x1_behav
// 
// Revision: 0.0
// Revision 0.01 - File Created
// Additional Comments: A conversion of MUX2X1 4bits
// 
//////////////////////////////////////////////////////////////////////////////////

module mux4x2_behav(                	 // starts behavorial module
    
	//INPUTS
	input wire clk,         				// clock in @f
	input wire [8:0] in0,					// datas in with valid at [0] pos
	input wire [8:0] in1,
	input wire [8:0] in2,
	input wire [8:0] in3,
	input reset,							// reset in

    //OUTPUTS
	output reg [8:0] out0,					// data out0
	output reg [8:0] out1					// data out1
 );
    
    //AUXILIARY/INTERNAL NODES
	wire [8:0] wout0;
	wire [8:0] wout1;

// Conection
mux2x1_behav mux_A(				.out(wout0),
								.in0(in0),
                        		.in1(in1),
								.reset(reset),
								.clk(clk)
);
 
mux2x1_behav mux_B(				.out(wout1),
								.in0(in2),
                        		.in1(in3),
								.reset(reset),
								.clk(clk)
);

//spreading final signal
always @ (*) begin
	out0 <=	wout0;
	out1 <=	wout1;
end

endmodule                               // Mux4x2

MUX4a2/tb.v
`timescale 1ns / 1ps
//////////////////////////////////////////////////////////////////////////////////
// Company: 
// Engineer: 
// 
// Create Date: 22.04.2020 00:56:45
// Design Name: 
// Module Name: bancoPruebas
// Project Name: 
// Target Devices: 
// Tool Versions: 
// Description: 
// 
// Dependencies: 
// 
// Revision:
// Revision 0.01 - File Created
// Additional Comments:
// 
//////////////////////////////////////////////////////////////////////////////////
`include "mux4x2_behav.v"
`include "tester.v"

module bancoPruebas();


wire [8:0] in0;	
wire [8:0] in1;
wire [8:0] in2;
wire [8:0] in3;
wire reset;	
wire clk;						
wire [8:0] out0;
wire [8:0] out1;


// conexiones e instanciado

mux4x2_behav	 	mux_behav(		                       
						.out0(out0),
						.out1(out1),
						.in0(in0),
                        .in1(in1),
						.in2(in2),
						.in3(in3),
						.reset(reset),
						.clk(clk)
);



tester Tb(       		.out0(out0),
						.out1(out1),
						.in0(in0),
                        .in1(in1),
						.in2(in2),
						.in3(in3),
						.reset(reset),
						.clk(clk)
);

endmodule

MUX4a2/muxy.vcd
$date
	Wed May 20 15:55:53 2020
$end
$version
	Icarus Verilog
$end
$timescale
	1ps
$end
$scope module bancoPruebas $end
$var wire 1 ! reset $end
$var wire 9 " out1 [8:0] $end
$var wire 9 # out0 [8:0] $end
$var wire 9 $ in3 [8:0] $end
$var wire 9 % in2 [8:0] $end
$var wire 9 & in1 [8:0] $end
$var wire 9 ' in0 [8:0] $end
$var wire 1 ( clk $end
$scope module Tb $end
$var wire 9 ) out1 [8:0] $end
$var wire 9 * out0 [8:0] $end
$var reg 1 ( clk $end
$var reg 4 + count0 [3:0] $end
$var reg 4 , count1 [3:0] $end
$var reg 9 - in0 [8:0] $end
$var reg 9 . in1 [8:0] $end
$var reg 9 / in2 [8:0] $end
$var reg 9 0 in3 [8:0] $end
$var reg 1 ! reset $end
$upscope $end
$scope module mux_behav $end
$var wire 1 ( clk $end
$var wire 9 1 in0 [8:0] $end
$var wire 9 2 in1 [8:0] $end
$var wire 9 3 in2 [8:0] $end
$var wire 9 4 in3 [8:0] $end
$var wire 1 ! reset $end
$var wire 9 5 wout1 [8:0] $end
$var wire 9 6 wout0 [8:0] $end
$var reg 9 7 out0 [8:0] $end
$var reg 9 8 out1 [8:0] $end
$scope module mux_A $end
$var wire 1 ( clk $end
$var wire 9 9 in0 [8:0] $end
$var wire 9 : in1 [8:0] $end
$var wire 1 ! reset $end
$var reg 9 ; out [8:0] $end
$var reg 1 < selector $end
$upscope $end
$scope module mux_B $end
$var wire 1 ( clk $end
$var wire 9 = in0 [8:0] $end
$var wire 9 > in1 [8:0] $end
$var wire 1 ! reset $end
$var reg 9 ? out [8:0] $end
$var reg 1 @ selector $end
$upscope $end
$upscope $end
$upscope $end
$enddefinitions $end
#0
$dumpvars
x@
bx ?
b1 >
b10101011 =
x<
bx ;
b1 :
b11111111 9
bx 8
bx 7
bx 6
bx 5
b1 4
b10101011 3
b1 2
b11111111 1
b1 0
b10101011 /
b1 .
b11111111 -
b0 ,
b0 +
bx *
bx )
0(
b11111111 '
b1 &
b10101011 %
b1 $
bx #
bx "
x!
$end
#2000
0!
#10000
b1 ,
b1 +
b10101011 "
b10101011 )
b10101011 8
b11111111 #
b11111111 *
b11111111 7
b11111111 6
b11111111 ;
b10101011 5
b10101011 ?
b111111110 '
b111111110 -
b111111110 1
b111111110 9
1!
1(
#20000
0(
#30000
b11111110 #
b11111110 *
b11111110 7
b10000 $
b10000 0
b10000 4
b10000 >
b1010100 %
b1010100 /
b1010100 3
b1010100 =
b1010100 '
b1010100 -
b1010100 1
b1010100 9
b0 &
b0 .
b0 2
b0 :
b11111110 6
b11111110 ;
1(
#40000
0(
#50000
b10101010 "
b10101010 )
b10101010 8
b10101010 5
b10101010 ?
b10001 $
b10001 0
b10001 4
b10001 >
b100001 %
b100001 /
b100001 3
b100001 =
b1000001 &
b1000001 .
b1000001 2
b1000001 :
b10000001 '
b10000001 -
b10000001 1
b10000001 9
1(
#60000
0(
#70000
b10 ,
b10 +
b100001 "
b100001 )
b100001 8
b10000001 #
b10000001 *
b10000001 7
b100001 5
b100001 ?
b10000001 6
b10000001 ;
1(
#80000
0(
#90000
1(
#100000
0(
#110000
1(
#120000
0(
#130000
b111111110 '
b111111110 -
b111111110 1
b111111110 9
1(
#140000
0(
#150000
b10000000 #
b10000000 *
b10000000 7
b10000 $
b10000 0
b10000 4
b10000 >
b1010100 %
b1010100 /
b1010100 3
b1010100 =
b1010100 '
b1010100 -
b1010100 1
b1010100 9
b1000000 &
b1000000 .
b1000000 2
b1000000 :
b10000000 6
b10000000 ;
1(
#160000
0(
#170000
b100000 "
b100000 )
b100000 8
b100000 5
b100000 ?
b10001 $
b10001 0
b10001 4
b10001 >
b100001 %
b100001 /
b100001 3
b100001 =
b1000001 &
b1000001 .
b1000001 2
b1000001 :
b10000001 '
b10000001 -
b10000001 1
b10000001 9
1(
#180000
0(
#190000
b11 ,
b11 +
b100001 "
b100001 )
b100001 8
b10000001 #
b10000001 *
b10000001 7
b100001 5
b100001 ?
b10000001 6
b10000001 ;
1(
