serieparalelo/IDL_COM/serieparalelo.v
`timescale 1ns / 1ps


//////////////////////////////////////////////////////////////////////////////////
// Company: U.C.R E.I.E
// Engineer: Brandon Esquivel Molina
// 
// Create Date: 26.05.2020
// Design Name: Serial to parallel Module 
// Module Name: Serial to parallel Module 
// Project Name: PHY Layer PCIe
// Target Devices: PCIe
// Tool Versions: Yosys 0.9 Iverolg release at 2020
// Description: 
// Dependencies:
// 
// Revision: 1.0  all good 
// Revision 0.01 - File Created
// Additional Comments: 
// 
//////////////////////////////////////////////////////////////////////////////////


module serieparaleloIDL(
    
    // INPUTS
    input wire in,                          // entradas de 1 bit a 32f
    input wire clk32f,                      // f max
    input wire clk4f,                       // f del paralelo 32f/8 datos = 4f
    input wire reset,
    // OUTPUTS
    output reg valido                           // salida dato valido
);   
    // INTERNAL/AUXILIARY
    reg [7:0] register;             // registro de datos de entrada a enviar
    reg [3:0] BC_counter;           // contador de Palabras BC 
    reg active;                     // indica comunicación activa entre los modulos
    //reg [7:0] out;
    
    always @( posedge clk32f ) begin
        if (~reset) begin
            register    <=  0;
        end else begin 
            register  <=  {register[6:0], in};  // registro desplazando bit a bit de entrada
        end
    end



    // POSEDGE CLKS
    always @(posedge clk4f) begin
        if (~reset) begin
            BC_counter   <=  0;          // condicion de reset para contador de BC
            valido       <=  0;          // set del valido de salida       
            //out          <=  0;          // salida a cero 
        end else begin

        // contador de BC 
        if (register == 'hBC) begin
                if (~active) begin                  // si no hay active
                    BC_counter  <= BC_counter + 1;  // contador aumenta
                end
            end else begin
                BC_counter  <= BC_counter;          // se cumple la condicion de active, se mantiene BC = 4
            end

    // Condicional para valid
        if(active && register != 'hBC) begin        // si hay active y el registro indica una palabra diferente de BC
                valido = 1;                          // se valida el dato/palabra
            end else begin
                valido = 0;                          // en otro caso, no
            end

   // Salidas         
   /* if ( valido ) begin
        //out <= register;                          // Trasegando dato
        //valid <= 1;
        end else begin
            //out <= out;                             // mantiene ultimo valor de salida en caso de valid = 0
            //valid <= 0;
        end*/
    end
end

// inicia logica combinacional
always @(*) begin                   // logica para la senal de active
if(BC_counter >= 4) begin      		// cuando se llega a 4 BC se activa active, en otro contador es cero, esto indica el control para el inicio de envio de palabras
    active = 1;
end else begin
     active = 0;
        end
    end

endmodule                   // serieparalelo

serieparalelo/IDL_COM/tester.v
//////////////////////////////////////////////////////////////////////////////////
// Company: U.C.R, EIE
// Engineer: Brandon Esquivel Molina
// 
// Create Date: 26.05.2020
// Design Name: Serial to parallel Module 
// Project Name: PHY Layer PCIe
// Target Devices: PCIe
// Tool Versions: Yosys 0.9 Iverolg release at 2020
// Description: tester for Serial to parallel module
// Dependencies: 
// 
// Revision: 1.0  All good
// Revision 0.01 - File Created
// Additional Comments: 
// 
//////////////////////////////////////////////////////////////////////////////////


module tester(
    input wire out,           // salida paralela de bus de 8 bits + valid
input wire outs,  
    input wire valid,               // + valid
    output reg in,                  // entrada bit a bit serial
    output reg reset,               // reset
    output reg clk32f,              // frecuencia mas rapida, de recepcion
    output reg clk4f                // frecuencia de envio

);
    
    // AUXILIARES
    reg clk16f;
    reg clk8f;
    reg clk2f;
    reg clk1f;
    reg clk;
    
    initial begin
		$dumpfile("muxy.vcd");																						// "dump" file
	$dumpvars;
	
        // reset 
        repeat(2) begin
        @(posedge clk32f);
        end
        @(posedge clk32f);
        reset = 1;                                
        repeat(2) begin
        @(posedge clk32f);
        end

        // pruebas 

        repeat(3) begin         // 01010101  -> NO HAY ACTIVE YA QUE BC < 4
        @(posedge clk32f);
        in  <=  ~in;
        end


        repeat(4) begin         // BC = 10 1111 00        
        @(posedge clk32f);
        in  <=  1;
        @(posedge clk32f);
        in  <=  0;
        @(posedge clk32f);
        in  <=  1;
        @(posedge clk32f);
        in  <=  1;
        @(posedge clk32f);
        in  <=  1;
        @(posedge clk32f);
        in  <=  1;
        @(posedge clk32f);
        in  <=  0;
        @(posedge clk32f);
        in  <=  0;
        end
        
        // EN ESTE PUNTO SE TIENEN 4 BC > ACTIVE = 1 Y SE RECIBE UNA PALABRA valida
        repeat(16) begin         // 10101010 -> AA 
        @(posedge clk32f);
        in  <=  ~in;
        end

        // Nueva palabra a enviar  -> EE -> 11101110
      @(posedge clk32f);
        in  <=  1;
        @(posedge clk32f);
        in  <=  1;
        @(posedge clk32f);
        in  <=  1;
        @(posedge clk32f);
        in  <=  0;
        @(posedge clk32f);
        in  <=  1;
        @(posedge clk32f);
        in  <=  1;
        @(posedge clk32f);
        in  <=  1;
        @(posedge clk32f);
        in  <=  0;


            // Nueva palabra a enviar FF 11111111
        @(posedge clk32f);
        in  <=  1;
        @(posedge clk32f);
        in  <=  1;
        @(posedge clk32f);
        in  <=  1;
        @(posedge clk32f);
        in  <=  1;
        @(posedge clk32f);
        in  <=  1;
        @(posedge clk32f);
        in  <=  1;
        @(posedge clk32f);
        in  <=  1;
        @(posedge clk32f);
        in  <=  1;
	


        repeat(4) begin         // BC = 10 1111 00        
        @(posedge clk32f);
        in  <=  1;
        @(posedge clk32f);
        in  <=  0;
        @(posedge clk32f);
        in  <=  1;
        @(posedge clk32f);
        in  <=  1;
        @(posedge clk32f);
        in  <=  1;
        @(posedge clk32f);
        in  <=  1;
        @(posedge clk32f);
        in  <=  0;
        @(posedge clk32f);
        in  <=  0;
        end


        $finish;
    end


	// Initial Values
	initial in			= 7'b0;	
	initial reset 		= 0;

	// clock logic
	initial	clk	 	    = 0;			// Initial value to avoid indeterminations
	always	#1 clk	    = ~clk;		// toggle every 1ns

	// clks 

	initial clk32f <= 0;
    initial clk16f <= 0;
    initial clk8f <= 0;
    initial clk4f <= 0;
    initial clk2f <= 0;
    initial clk1f <= 0;

	

	// checker
reg test;

always@(posedge clk) begin
    if(out != outs)
    begin
       $display ("ERROR behavioral file and structural file are not the same");
       test <= 1;
     end // end display

     else begin
        test <= 0;
      end //else
end // always checker



    // Faster frequency
    always @(posedge clk) begin
		clk32f <= ~clk32f; // if was LOW change to HIGH
        end 
    //////////////////////////////
    // For 16 Hz
    always @(posedge clk32f) begin
        clk16f <= ~clk16f; // if was LOW change to HIGH
        end
    //////////////////////////////
    // For 8 Hz
    always @(posedge clk16f) begin
            clk8f <= ~clk8f; // if was LOW change to HIGH
    end
    //////////////////////////////
    // For 4 Hz
    always @(posedge clk8f) begin
        clk4f <= ~clk4f; // if was LOW change to HIGH
        end
    //////////////////////////////
    // At 2 Hz
    always @(posedge clk4f) begin
        clk2f <= ~clk2f; // if was LOW change to HIGH
        end

    //////////////////////////////
    // At 1 HZ
    always @(posedge clk2f) begin
    clk1f <= ~clk1f; // if was LOW change to HIGH
 	end

endmodule // t_mux42

serieparalelo/IDL_COM/tb.v
`include "tester.v"
`include "serieparalelo.v"

module bancoPruebas();
    wire in;
    wire out;
    wire outs;
    wire reset;
    wire clk4f;
    wire clk32f;

tester Probador(
                    .out(out),
 		    .outs(outs),
                    .in(in),
                    .clk4f(clk4f),
                    .clk32f(clk32f),
                    .reset(reset)
              
    );

serieparaleloIDL spc (
                    .in(in),
                    .clk32f(clk32f),
                    .clk4f(clk4f),
                    .reset(reset),
                    .valido(out)
            
);

serieparaleloIDL sps (
                    .in(in),
                    .clk32f(clk32f),
                    .clk4f(clk4f),
                    .reset(reset),
                    .valido(outs)
                
);
endmodule

serieparalelo/IDL_COM/muxy.vcd
$date
	Tue Jun  2 01:28:57 2020
$end
$version
	Icarus Verilog
$end
$timescale
	1ps
$end
$scope module bancoPruebas $end
$var wire 1 ! reset $end
$var wire 1 " outs $end
$var wire 1 # out $end
$var wire 1 $ in $end
$var wire 1 % clk4f $end
$var wire 1 & clk32f $end
$scope module Probador $end
$var wire 1 ' valid $end
$var wire 1 " outs $end
$var wire 1 # out $end
$var reg 1 ( clk $end
$var reg 1 ) clk16f $end
$var reg 1 * clk1f $end
$var reg 1 + clk2f $end
$var reg 1 & clk32f $end
$var reg 1 % clk4f $end
$var reg 1 , clk8f $end
$var reg 1 $ in $end
$var reg 1 ! reset $end
$var reg 1 - test $end
$upscope $end
$scope module spc $end
$var wire 1 & clk32f $end
$var wire 1 % clk4f $end
$var wire 1 $ in $end
$var wire 1 ! reset $end
$var reg 4 . BC_counter [3:0] $end
$var reg 1 / active $end
$var reg 8 0 register [7:0] $end
$var reg 1 # valido $end
$upscope $end
$scope module sps $end
$var wire 1 & clk32f $end
$var wire 1 % clk4f $end
$var wire 1 $ in $end
$var wire 1 ! reset $end
$var reg 4 1 BC_counter [3:0] $end
$var reg 1 2 active $end
$var reg 8 3 register [7:0] $end
$var reg 1 " valido $end
$upscope $end
$upscope $end
$enddefinitions $end
#0
$dumpvars
bx 3
x2
bx 1
bx 0
x/
bx .
x-
0,
0+
0*
0)
0(
z'
0&
0%
0$
x#
x"
0!
$end
#1000000000000
1*
0/
02
1+
0#
b0 .
0"
b0 1
1%
1,
1)
b0 0
b0 3
0-
1&
1(
#2000000000000
0(
#3000000000000
0&
1(
#4000000000000
0(
#5000000000000
0)
1&
1(
#6000000000000
0(
#7000000000000
0&
1(
#8000000000000
0(
#9000000000000
0,
1)
1!
1&
1(
#10000000000000
0(
#11000000000000
0&
1(
#12000000000000
0(
#13000000000000
0)
1&
1(
#14000000000000
0(
#15000000000000
0&
1(
#16000000000000
0(
#17000000000000
0%
1,
1)
1&
1(
#18000000000000
0(
#19000000000000
0&
1(
#20000000000000
0(
#21000000000000
0)
1$
1&
1(
#22000000000000
0(
#23000000000000
0&
1(
#24000000000000
0(
#25000000000000
0,
0$
1)
b1 0
b1 3
1&
1(
#26000000000000
0(
#27000000000000
0&
1(
#28000000000000
0(
#29000000000000
b10 3
b10 0
0)
1$
1&
1(
#30000000000000
0(
#31000000000000
0&
1(
#32000000000000
0(
#33000000000000
0+
1%
1,
1)
b101 0
b101 3
1&
1(
#34000000000000
0(
#35000000000000
0&
1(
#36000000000000
0(
#37000000000000
b1011 3
b1011 0
0)
0$
1&
1(
#38000000000000
0(
#39000000000000
0&
1(
#40000000000000
0(
#41000000000000
0,
1$
1)
b10110 0
b10110 3
1&
1(
#42000000000000
0(
#43000000000000
0&
1(
#44000000000000
0(
#45000000000000
b101101 3
b101101 0
0)
1&
1(
#46000000000000
0(
#47000000000000
0&
1(
#48000000000000
0(
#49000000000000
0%
1,
1)
b1011011 0
b1011011 3
1&
1(
#50000000000000
0(
#51000000000000
0&
1(
#52000000000000
0(
#53000000000000
b10110111 3
b10110111 0
0)
1&
1(
#54000000000000
0(
#55000000000000
0&
1(
#56000000000000
0(
#57000000000000
0,
0$
1)
b1101111 0
b1101111 3
1&
1(
#58000000000000
0(
#59000000000000
0&
1(
#60000000000000
0(
#61000000000000
b11011110 3
b11011110 0
0)
1&
1(
#62000000000000
0(
#63000000000000
0&
1(
#64000000000000
0(
#65000000000000
0*
1+
b1 .
b1 1
1%
1,
1$
1)
b10111100 0
b10111100 3
1&
1(
#66000000000000
0(
#67000000000000
0&
1(
#68000000000000
0(
#69000000000000
b1111001 3
b1111001 0
0)
0$
1&
1(
#70000000000000
0(
#71000000000000
0&
1(
#72000000000000
0(
#73000000000000
0,
1$
1)
b11110010 0
b11110010 3
1&
1(
#74000000000000
0(
#75000000000000
0&
1(
#76000000000000
0(
#77000000000000
b11100101 3
b11100101 0
0)
1&
1(
#78000000000000
0(
#79000000000000
0&
1(
#80000000000000
0(
#81000000000000
0%
1,
1)
b11001011 0
b11001011 3
1&
1(
#82000000000000
0(
#83000000000000
0&
1(
#84000000000000
0(
#85000000000000
b10010111 3
b10010111 0
0)
1&
1(
#86000000000000
0(
#87000000000000
0&
1(
#88000000000000
0(
#89000000000000
0,
0$
1)
b101111 0
b101111 3
1&
1(
#90000000000000
0(
#91000000000000
0&
1(
#92000000000000
0(
#93000000000000
b1011110 3
b1011110 0
0)
1&
1(
#94000000000000
0(
#95000000000000
0&
1(
#96000000000000
0(
#97000000000000
b10 1
b10 .
0+
1%
1,
1$
1)
b10111100 0
b10111100 3
1&
1(
#98000000000000
0(
#99000000000000
0&
1(
#100000000000000
0(
#101000000000000
b1111001 3
b1111001 0
0)
0$
1&
1(
#102000000000000
0(
#103000000000000
0&
1(
#104000000000000
0(
#105000000000000
0,
1$
1)
b11110010 0
b11110010 3
1&
1(
#106000000000000
0(
#107000000000000
0&
1(
#108000000000000
0(
#109000000000000
b11100101 3
b11100101 0
0)
1&
1(
#110000000000000
0(
#111000000000000
0&
1(
#112000000000000
0(
#113000000000000
0%
1,
1)
b11001011 0
b11001011 3
1&
1(
#114000000000000
0(
#115000000000000
0&
1(
#116000000000000
0(
#117000000000000
b10010111 3
b10010111 0
0)
1&
1(
#118000000000000
0(
#119000000000000
0&
1(
#120000000000000
0(
#121000000000000
0,
0$
1)
b101111 0
b101111 3
1&
1(
#122000000000000
0(
#123000000000000
0&
1(
#124000000000000
0(
#125000000000000
b1011110 3
b1011110 0
0)
1&
1(
#126000000000000
0(
#127000000000000
0&
1(
#128000000000000
0(
#129000000000000
1*
1+
b11 .
b11 1
1%
1,
1$
1)
b10111100 0
b10111100 3
1&
1(
#130000000000000
0(
#131000000000000
0&
1(
#132000000000000
0(
#133000000000000
b1111001 3
b1111001 0
0)
0$
1&
1(
#134000000000000
0(
#135000000000000
0&
1(
#136000000000000
0(
#137000000000000
0,
1$
1)
b11110010 0
b11110010 3
1&
1(
#138000000000000
0(
#139000000000000
0&
1(
#140000000000000
0(
#141000000000000
b11100101 3
b11100101 0
0)
1&
1(
#142000000000000
0(
#143000000000000
0&
1(
#144000000000000
0(
#145000000000000
0%
1,
1)
b11001011 0
b11001011 3
1&
1(
#146000000000000
0(
#147000000000000
0&
1(
#148000000000000
0(
#149000000000000
b10010111 3
b10010111 0
0)
1&
1(
#150000000000000
0(
#151000000000000
0&
1(
#152000000000000
0(
#153000000000000
0,
0$
1)
b101111 0
b101111 3
1&
1(
#154000000000000
0(
#155000000000000
0&
1(
#156000000000000
0(
#157000000000000
b1011110 3
b1011110 0
0)
1&
1(
#158000000000000
0(
#159000000000000
0&
1(
#160000000000000
0(
#161000000000000
12
1/
b100 1
b100 .
0+
1%
1,
1$
1)
b10111100 0
b10111100 3
1&
1(
#162000000000000
0(
#163000000000000
0&
1(
#164000000000000
0(
#165000000000000
b1111001 3
b1111001 0
0)
0$
1&
1(
#166000000000000
0(
#167000000000000
0&
1(
#168000000000000
0(
#169000000000000
0,
1$
1)
b11110010 0
b11110010 3
1&
1(
#170000000000000
0(
#171000000000000
0&
1(
#172000000000000
0(
#173000000000000
b11100101 3
b11100101 0
0)
0$
1&
1(
#174000000000000
0(
#175000000000000
0&
1(
#176000000000000
0(
#177000000000000
0%
1,
1$
1)
b11001010 0
b11001010 3
1&
1(
#178000000000000
0(
#179000000000000
0&
1(
#180000000000000
0(
#181000000000000
b10010101 3
b10010101 0
0)
0$
1&
1(
#182000000000000
0(
#183000000000000
0&
1(
#184000000000000
0(
#185000000000000
0,
1$
1)
b101010 0
b101010 3
1&
1(
#186000000000000
0(
#187000000000000
0&
1(
#188000000000000
0(
#189000000000000
b1010101 3
b1010101 0
0)
0$
1&
1(
#190000000000000
0(
#191000000000000
0&
1(
#192000000000000
0(
#193000000000000
0*
1+
1#
1"
1%
1,
1$
1)
b10101010 0
b10101010 3
1&
1(
#194000000000000
0(
#195000000000000
0&
1(
#196000000000000
0(
#197000000000000
b1010101 3
b1010101 0
0)
0$
1&
1(
#198000000000000
0(
#199000000000000
0&
1(
#200000000000000
0(
#201000000000000
0,
1$
1)
b10101010 0
b10101010 3
1&
1(
#202000000000000
0(
#203000000000000
0&
1(
#204000000000000
0(
#205000000000000
b1010101 3
b1010101 0
0)
0$
1&
1(
#206000000000000
0(
#207000000000000
0&
1(
#208000000000000
0(
#209000000000000
0%
1,
1$
1)
b10101010 0
b10101010 3
1&
1(
#210000000000000
0(
#211000000000000
0&
1(
#212000000000000
0(
#213000000000000
b1010101 3
b1010101 0
0)
0$
1&
1(
#214000000000000
0(
#215000000000000
0&
1(
#216000000000000
0(
#217000000000000
0,
1$
1)
b10101010 0
b10101010 3
1&
1(
#218000000000000
0(
#219000000000000
0&
1(
#220000000000000
0(
#221000000000000
b1010101 3
b1010101 0
0)
0$
1&
1(
#222000000000000
0(
#223000000000000
0&
1(
#224000000000000
0(
#225000000000000
0+
1%
1,
1$
1)
b10101010 0
b10101010 3
1&
1(
#226000000000000
0(
#227000000000000
0&
1(
#228000000000000
0(
#229000000000000
b1010101 3
b1010101 0
0)
1&
1(
#230000000000000
0(
#231000000000000
0&
1(
#232000000000000
0(
#233000000000000
0,
1)
b10101011 0
b10101011 3
1&
1(
#234000000000000
0(
#235000000000000
0&
1(
#236000000000000
0(
#237000000000000
b1010111 3
b1010111 0
0)
0$
1&
1(
#238000000000000
0(
#239000000000000
0&
1(
#240000000000000
0(
#241000000000000
0%
1,
1$
1)
b10101110 0
b10101110 3
1&
1(
#242000000000000
0(
#243000000000000
0&
1(
#244000000000000
0(
#245000000000000
b1011101 3
b1011101 0
0)
1&
1(
#246000000000000
0(
#247000000000000
0&
1(
#248000000000000
0(
#249000000000000
0,
1)
b10111011 0
b10111011 3
1&
1(
#250000000000000
0(
#251000000000000
0&
1(
#252000000000000
0(
#253000000000000
b1110111 3
b1110111 0
0)
0$
1&
1(
#254000000000000
0(
#255000000000000
0&
1(
#256000000000000
0(
#257000000000000
1*
1+
1%
1,
1$
1)
b11101110 0
b11101110 3
1&
1(
#258000000000000
0(
#259000000000000
0&
1(
#260000000000000
0(
#261000000000000
b11011101 3
b11011101 0
0)
1&
1(
#262000000000000
0(
#263000000000000
0&
1(
#264000000000000
0(
#265000000000000
0,
1)
b10111011 0
b10111011 3
1&
1(
#266000000000000
0(
#267000000000000
0&
1(
#268000000000000
0(
#269000000000000
b1110111 3
b1110111 0
0)
1&
1(
#270000000000000
0(
#271000000000000
0&
1(
#272000000000000
0(
#273000000000000
0%
1,
1)
b11101111 0
b11101111 3
1&
1(
#274000000000000
0(
#275000000000000
0&
1(
#276000000000000
0(
#277000000000000
b11011111 3
b11011111 0
0)
1&
1(
#278000000000000
0(
#279000000000000
0&
1(
#280000000000000
0(
#281000000000000
0,
1)
b10111111 0
b10111111 3
1&
1(
#282000000000000
0(
#283000000000000
0&
1(
#284000000000000
0(
#285000000000000
b1111111 3
b1111111 0
0)
1&
1(
#286000000000000
0(
#287000000000000
0&
1(
#288000000000000
0(
#289000000000000
0+
1%
1,
1)
b11111111 0
b11111111 3
1&
1(
#290000000000000
0(
#291000000000000
0&
1(
#292000000000000
0(
#293000000000000
0)
0$
1&
1(
#294000000000000
0(
#295000000000000
0&
1(
#296000000000000
0(
#297000000000000
0,
1$
1)
b11111110 0
b11111110 3
1&
1(
#298000000000000
0(
#299000000000000
0&
1(
#300000000000000
0(
#301000000000000
b11111101 3
b11111101 0
0)
1&
1(
#302000000000000
0(
#303000000000000
0&
1(
#304000000000000
0(
#305000000000000
0%
1,
1)
b11111011 0
b11111011 3
1&
1(
#306000000000000
0(
#307000000000000
0&
1(
#308000000000000
0(
#309000000000000
b11110111 3
b11110111 0
0)
1&
1(
#310000000000000
0(
#311000000000000
0&
1(
#312000000000000
0(
#313000000000000
0,
0$
1)
b11101111 0
b11101111 3
1&
1(
#314000000000000
0(
#315000000000000
0&
1(
#316000000000000
0(
#317000000000000
b11011110 3
b11011110 0
0)
1&
1(
#318000000000000
0(
#319000000000000
0&
1(
#320000000000000
0(
#321000000000000
0*
1+
0#
0"
1%
1,
1$
1)
b10111100 0
b10111100 3
1&
1(
#322000000000000
0(
#323000000000000
0&
1(
#324000000000000
0(
#325000000000000
b1111001 3
b1111001 0
0)
0$
1&
1(
#326000000000000
0(
#327000000000000
0&
1(
#328000000000000
0(
#329000000000000
0,
1$
1)
b11110010 0
b11110010 3
1&
1(
#330000000000000
0(
#331000000000000
0&
1(
#332000000000000
0(
#333000000000000
b11100101 3
b11100101 0
0)
1&
1(
#334000000000000
0(
#335000000000000
0&
1(
#336000000000000
0(
#337000000000000
0%
1,
1)
b11001011 0
b11001011 3
1&
1(
#338000000000000
0(
#339000000000000
0&
1(
#340000000000000
0(
#341000000000000
b10010111 3
b10010111 0
0)
1&
1(
#342000000000000
0(
#343000000000000
0&
1(
#344000000000000
0(
#345000000000000
0,
0$
1)
b101111 0
b101111 3
1&
1(
#346000000000000
0(
#347000000000000
0&
1(
#348000000000000
0(
#349000000000000
b1011110 3
b1011110 0
0)
1&
1(
#350000000000000
0(
#351000000000000
0&
1(
#352000000000000
0(
#353000000000000
0+
1%
1,
1$
1)
b10111100 0
b10111100 3
1&
1(
#354000000000000
0(
#355000000000000
0&
1(
#356000000000000
0(
#357000000000000
b1111001 3
b1111001 0
0)
0$
1&
1(
#358000000000000
0(
#359000000000000
0&
1(
#360000000000000
0(
#361000000000000
0,
1$
1)
b11110010 0
b11110010 3
1&
1(
#362000000000000
0(
#363000000000000
0&
1(
#364000000000000
0(
#365000000000000
b11100101 3
b11100101 0
0)
1&
1(
#366000000000000
0(
#367000000000000
0&
1(
#368000000000000
0(
#369000000000000
0%
1,
1)
b11001011 0
b11001011 3
1&
1(
#370000000000000
0(
#371000000000000
0&
1(
#372000000000000
0(
#373000000000000
b10010111 3
b10010111 0
0)
1&
1(
#374000000000000
0(
#375000000000000
0&
1(
#376000000000000
0(
#377000000000000
0,
0$
1)
b101111 0
b101111 3
1&
1(
#378000000000000
0(
#379000000000000
0&
1(
#380000000000000
0(
#381000000000000
b1011110 3
b1011110 0
0)
1&
1(
#382000000000000
0(
#383000000000000
0&
1(
#384000000000000
0(
#385000000000000
1*
1+
1%
1,
1$
1)
b10111100 0
b10111100 3
1&
1(
#386000000000000
0(
#387000000000000
0&
1(
#388000000000000
0(
#389000000000000
b1111001 3
b1111001 0
0)
0$
1&
1(
#390000000000000
0(
#391000000000000
0&
1(
#392000000000000
0(
#393000000000000
0,
1$
1)
b11110010 0
b11110010 3
1&
1(
#394000000000000
0(
#395000000000000
0&
1(
#396000000000000
0(
#397000000000000
b11100101 3
b11100101 0
0)
1&
1(
#398000000000000
0(
#399000000000000
0&
1(
#400000000000000
0(
#401000000000000
0%
1,
1)
b11001011 0
b11001011 3
1&
1(
#402000000000000
0(
#403000000000000
0&
1(
#404000000000000
0(
#405000000000000
b10010111 3
b10010111 0
0)
1&
1(
#406000000000000
0(
#407000000000000
0&
1(
#408000000000000
0(
#409000000000000
0,
0$
1)
b101111 0
b101111 3
1&
1(
#410000000000000
0(
#411000000000000
0&
1(
#412000000000000
0(
#413000000000000
b1011110 3
b1011110 0
0)
1&
1(
