MUX2a1/Comparacion de modelos/tester.v
`timescale 1ns / 1ps
//////////////////////////////////////////////////////////////////////////////////
// Company: U.C.R E.I.E
// Engineer: Brandon Esquivel Molina
// 
// Create Date: 19.05.2020
// Design Name: mux2x1_8bits+VALID with automatic selector
// Module Name: Tester for mux2x1 8BITS + VALID
// Project Name: PHY Layer PCIe
// Target Devices: PCIe
// Tool Versions: Yosys 0.9 Iverolg release at 2020
// Description: tester for module Mux2x1 8bits+ valid a submodule in mux4x2 8bits + valid first level L1
// Dependencies: mux2x1_behav
// 
// Revision: 1.0  -> Change Sruct of valid, putting out of Ins busses
// Revision 0.01 - File Created
// Additional Comments: A conversion of MUX2X1 4bits
// 
//////////////////////////////////////////////////////////////////////////////////


module tester(
	//OUTPUTS
output reg [7:0] in0,
output reg [7:0] in1,
output reg [1:0] valid,
output reg clk,
output reg reset,
	//INPUTS
input [7:0] outc,
input [7:0] outs
);

reg [3:0] count;

initial begin
		$dumpfile("muxy.vcd");																						// "dump" file
		$dumpvars;																									// "dumpping" variables
		$display ("clk,\tin0,\tin1,\tvalid,\toutc,\touts,\tcount,\treset,\tchecker");														// print onces
		$monitor($time,"%b\t\t%b\t\t%b\t%b\t%b\t%b\t%b\t%b", clk, in0, in1, valid, outc, outs, checker, count,reset); 							// print everytime	
				
		repeat (2) begin
		@(posedge clk);	
		@(posedge clk);				// test for reset	- wait 3 cicles with reset 0 to avoid Flipflops errors																			// sync with clock																		
		{in1} <= {in1}+1;
		{in0} <= {in0}-1;
		end
		reset = 1;					// test for reset
		repeat (3) begin			// Repeat cycles without changes. reset 
		@(posedge clk);
		end
		repeat (6) begin			// Repeat the test 4 times to see the general behave
		@(posedge clk);				// sync with clock reset 1, valid 11
		//{in1} <= {in1}+1;			// change the inputs	 	
		//{in0} <= {in0}-1;	
		end	

		repeat (7) begin
		@(posedge clk);				// testing valid			
		{in1} <= {in1}+1;
		{in0} <= {in0}-1;															
		{valid} <= {valid}+1;
		end
		

       	$finish;													// save variables finish
		end																// initial begin
	

	

	// Initial Values
	initial	in0			<= 7'b0;
	initial in1			<= 7'b0;
	initial valid		<= 2'b11;	
	initial #10 reset 	<= 0;

	// clock logic
	initial	clk	 		<= 0;			// Initial value to avoid indeterminations
	always	#10 clk 	<= ~clk;		// toggle every 10ns

	// Positive Transitions Counter
	initial count <= 0;
	always@(posedge outc) begin
	count<=count+1;
	end	




	// Model checker - > if reg checker is 1 means that struct and behavorial models have the same output 

	reg checker;
	always@(posedge clk) begin
    	if(outc != outs)
    	begin
       $display ("ERROR behavioral file and structural file are not the same");
       checker <= 0;
     	end // end display
     else begin
        checker <= 1;
      end //else
end // always checker



endmodule

MUX2a1/Comparacion de modelos/mux2x1_struct.v
/* Generated by Yosys 0.9 (git sha1 UNKNOWN, gcc 7.5.0-3ubuntu1~18.04 -fPIC -Os) */
`include "cmos_cells.v" 

(* top =  1  *)
(* src = "mux2x1_struct.v:21" *)
module mux2x1_struct(clk, in0, in1, valid, reset, out);
  (* src = "mux2x1_struct.v:43" *)
  wire [7:0] _00_;
  (* src = "mux2x1_struct.v:43" *)
  wire _01_;
  (* src = "mux2x1_struct.v:48" *)
  wire _02_;
  wire [7:0] _03_;
  wire [7:0] _04_;
  wire [7:0] _05_;
  (* src = "mux2x1_struct.v:24" *)
  input clk;
  (* src = "mux2x1_struct.v:25" *)
  input [7:0] in0;
  (* src = "mux2x1_struct.v:26" *)
  input [7:0] in1;
  (* src = "mux2x1_struct.v:31" *)
  output [7:0] out;
  (* src = "mux2x1_struct.v:28" *)
  input reset;
  (* src = "mux2x1_struct.v:35" *)
  wire selector;
  (* src = "mux2x1_struct.v:27" *)
  input [1:0] valid;
  assign _04_[0] = valid[0] ? (* src = "mux2x1_struct.v:56" *) in0[0] : out[0];
  assign _04_[1] = valid[0] ? (* src = "mux2x1_struct.v:56" *) in0[1] : out[1];
  assign _04_[2] = valid[0] ? (* src = "mux2x1_struct.v:56" *) in0[2] : out[2];
  assign _04_[3] = valid[0] ? (* src = "mux2x1_struct.v:56" *) in0[3] : out[3];
  assign _04_[4] = valid[0] ? (* src = "mux2x1_struct.v:56" *) in0[4] : out[4];
  assign _04_[5] = valid[0] ? (* src = "mux2x1_struct.v:56" *) in0[5] : out[5];
  assign _04_[6] = valid[0] ? (* src = "mux2x1_struct.v:56" *) in0[6] : out[6];
  assign _04_[7] = valid[0] ? (* src = "mux2x1_struct.v:56" *) in0[7] : out[7];
  assign _05_[0] = valid[1] ? (* src = "mux2x1_struct.v:50" *) in1[0] : out[0];
  assign _05_[1] = valid[1] ? (* src = "mux2x1_struct.v:50" *) in1[1] : out[1];
  assign _05_[2] = valid[1] ? (* src = "mux2x1_struct.v:50" *) in1[2] : out[2];
  assign _05_[3] = valid[1] ? (* src = "mux2x1_struct.v:50" *) in1[3] : out[3];
  assign _05_[4] = valid[1] ? (* src = "mux2x1_struct.v:50" *) in1[4] : out[4];
  assign _05_[5] = valid[1] ? (* src = "mux2x1_struct.v:50" *) in1[5] : out[5];
  assign _05_[6] = valid[1] ? (* src = "mux2x1_struct.v:50" *) in1[6] : out[6];
  assign _05_[7] = valid[1] ? (* src = "mux2x1_struct.v:50" *) in1[7] : out[7];
  assign _03_[0] = selector ? (* src = "mux2x1_struct.v:49" *) _05_[0] : _04_[0];
  assign _03_[1] = selector ? (* src = "mux2x1_struct.v:49" *) _05_[1] : _04_[1];
  assign _03_[2] = selector ? (* src = "mux2x1_struct.v:49" *) _05_[2] : _04_[2];
  assign _03_[3] = selector ? (* src = "mux2x1_struct.v:49" *) _05_[3] : _04_[3];
  assign _03_[4] = selector ? (* src = "mux2x1_struct.v:49" *) _05_[4] : _04_[4];
  assign _03_[5] = selector ? (* src = "mux2x1_struct.v:49" *) _05_[5] : _04_[5];
  assign _03_[6] = selector ? (* src = "mux2x1_struct.v:49" *) _05_[6] : _04_[6];
  assign _03_[7] = selector ? (* src = "mux2x1_struct.v:49" *) _05_[7] : _04_[7];
  assign _00_[0] = reset ? (* src = "mux2x1_struct.v:44" *) _03_[0] : 1'h0;
  assign _00_[1] = reset ? (* src = "mux2x1_struct.v:44" *) _03_[1] : 1'h0;
  assign _00_[2] = reset ? (* src = "mux2x1_struct.v:44" *) _03_[2] : 1'h0;
  assign _00_[3] = reset ? (* src = "mux2x1_struct.v:44" *) _03_[3] : 1'h0;
  assign _00_[4] = reset ? (* src = "mux2x1_struct.v:44" *) _03_[4] : 1'h0;
  assign _00_[5] = reset ? (* src = "mux2x1_struct.v:44" *) _03_[5] : 1'h0;
  assign _00_[6] = reset ? (* src = "mux2x1_struct.v:44" *) _03_[6] : 1'h0;
  assign _00_[7] = reset ? (* src = "mux2x1_struct.v:44" *) _03_[7] : 1'h0;
  assign _01_ = reset ? (* src = "mux2x1_struct.v:44" *) _02_ : 1'h0;
  assign _02_ = ~(* src = "mux2x1_struct.v:48" *) selector;
  (* src = "mux2x1_struct.v:43" *)
  DFF _40_ (
    .C(clk),
    .D(_00_[0]),
    .Q(out[0])
  );
  (* src = "mux2x1_struct.v:43" *)
  DFF _41_ (
    .C(clk),
    .D(_00_[1]),
    .Q(out[1])
  );
  (* src = "mux2x1_struct.v:43" *)
  DFF _42_ (
    .C(clk),
    .D(_00_[2]),
    .Q(out[2])
  );
  (* src = "mux2x1_struct.v:43" *)
  DFF _43_ (
    .C(clk),
    .D(_00_[3]),
    .Q(out[3])
  );
  (* src = "mux2x1_struct.v:43" *)
  DFF _44_ (
    .C(clk),
    .D(_00_[4]),
    .Q(out[4])
  );
  (* src = "mux2x1_struct.v:43" *)
  DFF _45_ (
    .C(clk),
    .D(_00_[5]),
    .Q(out[5])
  );
  (* src = "mux2x1_struct.v:43" *)
  DFF _46_ (
    .C(clk),
    .D(_00_[6]),
    .Q(out[6])
  );
  (* src = "mux2x1_struct.v:43" *)
  DFF _47_ (
    .C(clk),
    .D(_00_[7]),
    .Q(out[7])
  );
  (* src = "mux2x1_struct.v:43" *)
  DFF _48_ (
    .C(clk),
    .D(_01_),
    .Q(selector)
  );
endmodule

MUX2a1/Comparacion de modelos/mux2x1_behav.v
`timescale 1ns / 1ps
//////////////////////////////////////////////////////////////////////////////////
// Company: U.C.R EIE
// Engineer: Brandon Esquivel Molina
// 
// Create Date: 19.05.2020
// Design Name: mux2x1_8bits+VALID with automatic selector
// Module Name: mux2x1 8BITS + VALID
// Project Name: PHY Layer PCIe
// Target Devices: PCIe
// Tool Versions: Yosys 0.9 Iverolg release at 2020
// Description: module Mux2x1 8bits+ valid a submodule in mux4x2 8bits + valid first level L1
// Dependencies: 
// 
// Revision: 1.0 VALID OUT OF DATA IN BUS
// Revision 0.01 - File Created
// Additional Comments: A conversion of MUX2X1 4bits
// 
//////////////////////////////////////////////////////////////////////////////////

module mux2x1_behav(                 		// starts behavorial module
    
	//INPUTS
	input wire clk,         				// clock in @f
	input wire [7:0] in0,					// datas in
	input wire [7:0] in1,
	input wire [1:0] valid,					// valid bits for the inputs
	input reset,							// reset in

	//OUTPUTS
	output reg [7:0] out					// data out
 );
    
	//AUXILIARY
	reg selector;								// automatic selector
    
    // AUTOMATIC SELECTOR LOGIC
	//always @(posedge clk) begin					// triggered at clk or by pressing the reset button
	


	// SEQUENTIAL LOGIC START
	always @ (posedge clk) begin 
		if (~reset) begin
            selector <= 0;						// reset condition default
			out <= 0;
		end else begin
			selector <= ~selector;				// make toggle at posedge clock
			if(selector) begin								// MUX select in1 
				if(valid[1]) begin							// checking valid bit for in1
					out <= in1;								// spreading signal in1
				end else begin
							out <= out;						// if valid = 0 keep the last dataout
						end
			end else begin									// MUX select in0
				if (valid[0]) begin							// checking valid bit for in0
					out <= in0;								// spreading signal in0
				end 
				else begin
					out <= out;								// if valid=0 keep the last dataout.
				end
			end 
		end
	end

endmodule                               // MUX2X1

MUX2a1/Comparacion de modelos/tb.v
`timescale 1ns / 1ps
//////////////////////////////////////////////////////////////////////////////////
// Company: 
// Engineer: 
// 
// Create Date: 22.04.2020 00:56:45
// Design Name: 
// Module Name: bancoPruebas
// Project Name: 
// Target Devices: 
// Tool Versions: 
// Description: 
// 
// Dependencies: 
// 
// Revision:
// Revision 0.01 - File Created
// Additional Comments:
// 
//////////////////////////////////////////////////////////////////////////////////
`include "mux2x1_behav.v"
`include "mux2x1_struct.v"
`include "tester.v"

module bancoPruebas();
// conexiones de salidas

wire [7:0] in0;			// cable de entrada 1
wire [7:0] in1;			// cable de entrada 2
wire clk;				// reloj
wire [7:0] outc;		// salida conductual
wire [7:0] outs;		// salida estructural
wire reset;				// reset
wire [1:0] valid;		// valid 
// conexiones e instanciado

mux2x1_behav	 	mux_behav(		                       
						.out(outc),
						.in0(in0),
                        .in1(in1),
						.valid(valid),
						.reset(reset),
						.clk(clk)
);


mux2x1_struct 		mux_struct (
						.out(outs),
						.in0(in0),
                        .in1(in1),
						.valid(valid),
						.reset(reset),
						.clk(clk)
);



tester Tb(       	.outc(outc),
					.outs(outs),
					.in0(in0),
                    .in1(in1),
					.valid(valid),
					.reset(reset),
					.clk(clk)
);

endmodule

MUX2a1/Comparacion de modelos/cmos_cells.v
 module BUF(A, Y);
input A;
output Y;
assign Y = A;
endmodule

module NOT(A, Y);
input A;
output Y;
assign Y = ~A;
endmodule

module NAND(A, B, Y);
input A, B;
output Y;
assign Y = ~(A & B);
endmodule

module NOR(A, B, Y);
input A, B;
output Y;
assign Y = ~(A | B);
endmodule

module DFF(C, D, Q);
input C, D;
output reg Q;
always @(posedge C)
	Q <= D;
endmodule

module DFFSR(C, D, Q, S, R);
input C, D, S, R;
output reg Q;
always @(posedge C, posedge S, posedge R)
	if (S)
		Q <= 1'b1;
	else if (R)
		Q <= 1'b0;
	else
		Q <= D;
endmodule

MUX2a1/Comparacion de modelos/muxy.vcd
$date
	Fri May 22 13:44:11 2020
$end
$version
	Icarus Verilog
$end
$timescale
	1ps
$end
$scope module BUF $end
$var wire 1 ! A $end
$var wire 1 " Y $end
$upscope $end
$scope module DFFSR $end
$var wire 1 # C $end
$var wire 1 $ D $end
$var wire 1 % R $end
$var wire 1 & S $end
$var reg 1 ' Q $end
$upscope $end
$scope module NAND $end
$var wire 1 ( A $end
$var wire 1 ) B $end
$var wire 1 * Y $end
$upscope $end
$scope module NOR $end
$var wire 1 + A $end
$var wire 1 , B $end
$var wire 1 - Y $end
$upscope $end
$scope module NOT $end
$var wire 1 . A $end
$var wire 1 / Y $end
$upscope $end
$scope module bancoPruebas $end
$var wire 2 0 valid [1:0] $end
$var wire 1 1 reset $end
$var wire 8 2 outs [7:0] $end
$var wire 8 3 outc [7:0] $end
$var wire 8 4 in1 [7:0] $end
$var wire 8 5 in0 [7:0] $end
$var wire 1 6 clk $end
$scope module Tb $end
$var wire 8 7 outs [7:0] $end
$var wire 8 8 outc [7:0] $end
$var reg 1 9 checker $end
$var reg 1 6 clk $end
$var reg 4 : count [3:0] $end
$var reg 8 ; in0 [7:0] $end
$var reg 8 < in1 [7:0] $end
$var reg 1 1 reset $end
$var reg 2 = valid [1:0] $end
$upscope $end
$scope module mux_behav $end
$var wire 1 6 clk $end
$var wire 8 > in0 [7:0] $end
$var wire 8 ? in1 [7:0] $end
$var wire 1 1 reset $end
$var wire 2 @ valid [1:0] $end
$var reg 8 A out [7:0] $end
$var reg 1 B selector $end
$upscope $end
$scope module mux_struct $end
$var wire 1 C _02_ $end
$var wire 1 6 clk $end
$var wire 8 D in0 [7:0] $end
$var wire 8 E in1 [7:0] $end
$var wire 1 1 reset $end
$var wire 2 F valid [1:0] $end
$var wire 1 G selector $end
$var wire 8 H out [7:0] $end
$var wire 8 I _05_ [7:0] $end
$var wire 8 J _04_ [7:0] $end
$var wire 8 K _03_ [7:0] $end
$var wire 1 L _01_ $end
$var wire 8 M _00_ [7:0] $end
$scope module _40_ $end
$var wire 1 6 C $end
$var wire 1 N D $end
$var reg 1 O Q $end
$upscope $end
$scope module _41_ $end
$var wire 1 6 C $end
$var wire 1 P D $end
$var reg 1 Q Q $end
$upscope $end
$scope module _42_ $end
$var wire 1 6 C $end
$var wire 1 R D $end
$var reg 1 S Q $end
$upscope $end
$scope module _43_ $end
$var wire 1 6 C $end
$var wire 1 T D $end
$var reg 1 U Q $end
$upscope $end
$scope module _44_ $end
$var wire 1 6 C $end
$var wire 1 V D $end
$var reg 1 W Q $end
$upscope $end
$scope module _45_ $end
$var wire 1 6 C $end
$var wire 1 X D $end
$var reg 1 Y Q $end
$upscope $end
$scope module _46_ $end
$var wire 1 6 C $end
$var wire 1 Z D $end
$var reg 1 [ Q $end
$upscope $end
$scope module _47_ $end
$var wire 1 6 C $end
$var wire 1 \ D $end
$var reg 1 ] Q $end
$upscope $end
$scope module _48_ $end
$var wire 1 6 C $end
$var wire 1 L D $end
$var reg 1 G Q $end
$upscope $end
$upscope $end
$upscope $end
$enddefinitions $end
#0
$dumpvars
x]
0\
x[
0Z
xY
0X
xW
0V
xU
0T
xS
0R
xQ
0P
xO
0N
b0 M
xL
b0 K
b0 J
b0 I
bx H
xG
b11 F
b0 E
b0 D
xC
xB
bx A
b11 @
b0 ?
b0 >
b11 =
b0 <
b0 ;
b0 :
x9
bx 8
bx 7
06
b0 5
b0 4
bx 3
bx 2
x1
b11 0
z/
z.
x-
z,
z+
x*
z)
z(
x'
z&
z%
z$
z#
z"
z!
$end
#10000
1C
b0 3
b0 8
b0 A
0B
0O
0Q
0S
0U
0W
0Y
0[
b0 2
b0 7
b0 H
0]
0G
19
0L
16
01
#20000
06
#30000
16
#40000
06
#50000
16
#60000
06
#70000
b11111111 K
b11111111 J
b1 I
b11111111 5
b11111111 ;
b11111111 >
b11111111 D
b1 4
b1 <
b1 ?
b1 E
16
#80000
06
#90000
16
#100000
06
#110000
16
#120000
06
#130000
16
#140000
06
#150000
b11111110 K
b11111110 J
b10 I
b11111110 5
b11111110 ;
b11111110 >
b11111110 D
b10 4
b10 <
b10 ?
b10 E
16
#160000
06
#170000
16
#180000
06
#190000
16
#200000
06
#210000
16
#220000
06
#230000
1N
b11111101 K
b11111101 J
b11 I
b11111101 5
b11111101 ;
b11111101 >
b11111101 D
b11 4
b11 <
b11 ?
b11 E
0P
1R
1T
1V
1X
1Z
1\
b11111101 M
1L
11
16
#240000
06
#250000
b1 :
0\
0Z
0X
0V
0T
0R
1P
b11 M
0L
b11 K
0C
b11111101 3
b11111101 8
b11111101 A
1B
1O
1S
1U
1W
1Y
1[
b11111101 2
b11111101 7
b11111101 H
1]
1G
16
#260000
06
#270000
1\
1Z
1X
1V
1T
1R
0P
b11111101 M
1L
b11111101 K
1C
0G
0]
0[
0Y
0W
0U
0S
b11 2
b11 7
b11 H
1Q
b11 3
b11 8
b11 A
0B
16
#280000
06
#290000
0\
0Z
0X
0V
0T
0R
1P
b11 M
0L
b11 K
0C
b11111101 3
b11111101 8
b11111101 A
1B
0Q
1S
1U
1W
1Y
1[
b11111101 2
b11111101 7
b11111101 H
1]
1G
16
#300000
06
#310000
1\
1Z
1X
1V
1T
1R
0P
b11111101 M
1L
b11111101 K
1C
0G
0]
0[
0Y
0W
0U
0S
b11 2
b11 7
b11 H
1Q
b11 3
b11 8
b11 A
0B
16
#320000
06
#330000
1\
1Z
1X
1V
1T
1R
0P
b11111101 M
0L
b11111101 I
b11111101 K
0C
b11111101 3
b11111101 8
b11111101 A
1B
0Q
1S
1U
1W
1Y
1[
b11111101 2
b11111101 7
b11111101 H
1]
1G
b0 0
b0 =
b0 @
b0 F
b11111100 5
b11111100 ;
b11111100 >
b11111100 D
b100 4
b100 <
b100 ?
b100 E
16
#340000
06
#350000
1P
0R
b11111011 M
b11111011 K
b11111011 J
1L
1C
b1 0
b1 =
b1 @
b1 F
b11111011 5
b11111011 ;
b11111011 >
b11111011 D
b101 4
b101 <
b101 ?
b101 E
0G
0B
16
#360000
06
#370000
0N
0T
0V
0X
0Z
0\
1R
1P
b110 M
0L
b110 I
b110 K
0C
b11111011 3
b11111011 8
b11111011 A
1B
1Q
b11111011 2
b11111011 7
b11111011 H
0S
1G
b10 0
b10 =
b10 @
b10 F
b11111010 5
b11111010 ;
b11111010 >
b11111010 D
b110 4
b110 <
b110 ?
b110 E
16
#380000
06
#390000
0P
1\
1Z
1X
1V
1T
0R
1N
b11111001 M
b11111001 J
b111 I
1L
b11111001 K
1C
b11 0
b11 =
b11 @
b11 F
b11111001 5
b11111001 ;
b11111001 >
b11111001 D
b111 4
b111 <
b111 ?
b111 E
0G
0]
0[
0Y
0W
0U
1S
b110 2
b110 7
b110 H
0O
b110 3
b110 8
b110 A
0B
16
#400000
06
#410000
b10 :
1\
1Z
1X
1V
1T
0R
0P
b11111001 M
0L
b11111001 I
b11111001 K
0C
b11111001 3
b11111001 8
b11111001 A
1B
1O
0Q
0S
1U
1W
1Y
1[
b11111001 2
b11111001 7
b11111001 H
1]
1G
b0 0
b0 =
b0 @
b0 F
b11111000 5
b11111000 ;
b11111000 >
b11111000 D
b1000 4
b1000 <
b1000 ?
b1000 E
16
#420000
06
#430000
1P
1R
0T
b11110111 M
b11110111 K
b11110111 J
1L
1C
b1 0
b1 =
b1 @
b1 F
b11110111 5
b11110111 ;
b11110111 >
b11110111 D
b1001 4
b1001 <
b1001 ?
b1001 E
0G
0B
16
#440000
06
#450000
0N
0V
0X
0Z
0\
1T
0R
1P
b1010 M
0L
b1010 I
b1010 K
0C
b11110111 3
b11110111 8
b11110111 A
1B
1Q
1S
b11110111 2
b11110111 7
b11110111 H
0U
1G
b10 0
b10 =
b10 @
b10 F
b11110110 5
b11110110 ;
b11110110 >
b11110110 D
b1010 4
b1010 <
b1010 ?
b1010 E
16
