MUX2a1/conductual/tester.v
`timescale 1ns / 1ps
//////////////////////////////////////////////////////////////////////////////////
// Company: U.C.R E.I.E
// Engineer: Brandon Esquivel Molina
// 
// Create Date: 19.05.2020
// Design Name: mux2x1_8bits+VALID with automatic selector
// Module Name: Tester for mux2x1 8BITS + VALID
// Project Name: PHY Layer PCIe
// Target Devices: PCIe
// Tool Versions: Yosys 0.9 Iverolg release at 2020
// Description: tester for module Mux2x1 8bits+ valid a submodule in mux4x2 8bits + valid first level L1
// Dependencies: mux2x1_behav
// 
// Revision: 1.0  -> Change Sruct of valid, putting out of Ins busses
// Revision 0.01 - File Created
// Additional Comments: A conversion of MUX2X1 4bits
// 
//////////////////////////////////////////////////////////////////////////////////


module tester(
	//OUTPUTS
output reg [7:0] in0,
output reg [7:0] in1,
output reg [1:0] valid,
output reg clk,
output reg reset,
	//INPUTS
input [7:0] out
);

reg [3:0] count;

initial begin
		$dumpfile("muxy.vcd");																						// "dump" file
		$dumpvars;																									// "dumpping" variables
		$display ("clk,\tin0,\tin1,\tvalid,\tout,\tcount,\treset");														// print onces
		$monitor($time,"%b\t\t%b\t\t%b\t%b\t%b\t%b", clk, in0, in1, valid, out, count,reset); 							// print everytime	
				
		repeat (3) begin
		@(posedge clk);				// test for reset	- wait 3 cicles with reset 0 to avoid Flipflops errors																			// sync with clock																		
		{in1} <= {in1}+1;
		{in0} <= {in0}-1;
		end
		reset = 1;					// test for reset
		
		repeat (4) begin			// Repeat the test 4 times to see de general behave
		@(posedge clk);				// sync with clock reset 1, valid 11
		//{in1} <= {in1}+1;			// change the inputs	 	
		//{in0} <= {in0}-1;	
		end	

		repeat (7) begin
		@(posedge clk);				// testing valid			
		{in1} <= {in1}+1;
		{in0} <= {in0}-1;															
		{valid} <= {valid}+1;
		end
		

       	$finish;													// save variables finish
		end																// initial begin
	

	

	// Initial Values
	initial	in0			<= 7'b0;
	initial in1			<= 7'b0;
	initial valid		<= 2'b11;	
	initial #10 reset 	<= 0;

	// clock logic
	initial	clk	 		<= 0;			// Initial value to avoid indeterminations
	always	#10 clk 	<= ~clk;		// toggle every 10ns

	// Positive Transitions Counter
	initial count <= 0;
	always@(posedge out) begin
	count<=count+1;
	end	
endmodule

MUX2a1/conductual/mux2x1_behav.v
`timescale 1ns / 1ps
//////////////////////////////////////////////////////////////////////////////////
// Company: U.C.R EIE
// Engineer: Brandon Esquivel Molina
// 
// Create Date: 19.05.2020
// Design Name: mux2x1_8bits+VALID with automatic selector
// Module Name: mux2x1 8BITS + VALID
// Project Name: PHY Layer PCIe
// Target Devices: PCIe
// Tool Versions: Yosys 0.9 Iverolg release at 2020
// Description: module Mux2x1 8bits+ valid a submodule in mux4x2 8bits + valid first level L1
// Dependencies: 
// 
// Revision: 0.0
// Revision 0.01 - File Created
// Additional Comments: A conversion of MUX2X1 4bits
// 
//////////////////////////////////////////////////////////////////////////////////

module mux2x1_behav(                 		// starts behavorial module
    
	//INPUTS
	input wire clk,         				// clock in @f
	input wire [7:0] in0,					// datas in
	input wire [7:0] in1,
	input wire [1:0] valid,					// valid bits for the inputs
	input reset,							// reset in

	//OUTPUTS
	output reg [7:0] out					// data out
 );
    
	//AUXILIARY
	reg selector;								// automatic selector
    
    // AUTOMATIC SELECTOR LOGIC
	always @(posedge clk) begin					// triggered at clk or by pressing the reset button
		if(~reset) begin
			selector <= 0;						// reset condition default
        end	else begin
			selector <= ~selector;				// make toggle at posedge clock
        	end
    	end


	// SEQUENTIAL LOGIC START
	always @ (posedge clk) begin         	
		if (~reset) begin
            out <= 0;
		end else begin
			if(selector) begin								// MUX select in1 
				if(valid[1]) begin							// checking valid bit for in1
					out <= in1;								// spreading signal in1
				end else begin
							out <= out;						// if valid = 0 keep the last dataout
						end
			end else begin									// MUX select in0
				if (valid[0]) begin							// checking valid bit for in0
					out <= in0;								// spreading signal in0
				end 
				else begin
					out <= out;								// if valid=0 keep the last dataout.
				end
			end 
		end
	end

endmodule                               // MUX2X1

MUX2a1/conductual/tb.v
`timescale 1ns / 1ps
//////////////////////////////////////////////////////////////////////////////////
// Company: 
// Engineer: 
// 
// Create Date: 22.04.2020 00:56:45
// Design Name: 
// Module Name: bancoPruebas
// Project Name: 
// Target Devices: 
// Tool Versions: 
// Description: 
// 
// Dependencies: 
// 
// Revision:
// Revision 0.01 - File Created
// Additional Comments:
// 
//////////////////////////////////////////////////////////////////////////////////
`include "mux2x1_behav.v"
`include "tester.v"

module bancoPruebas();
// conexiones de salidas

wire [7:0] in0;			// cable de entrada 1
wire [7:0] in1;			// cable de entrada 2
wire clk;				// reloj
wire [7:0] out;			// salida conductual
wire reset;				// reset
wire [1:0] valid;		// valid 
// conexiones e instanciado

mux2x1_behav	 	mux_behav(		                       
						.out(out),
						.in0(in0),
                        .in1(in1),
						.valid(valid),
						.reset(reset),
						.clk(clk)
);



tester Tb(       	.out(out),
					.in0(in0),
                    .in1(in1),
					.valid(valid),
					.reset(reset),
					.clk(clk)
);

endmodule

MUX2a1/conductual/muxy.vcd
$date
	Tue May 26 19:57:29 2020
$end
$version
	Icarus Verilog
$end
$timescale
	1ps
$end
$scope module bancoPruebas $end
$var wire 2 ! valid [1:0] $end
$var wire 1 " reset $end
$var wire 8 # out [7:0] $end
$var wire 8 $ in1 [7:0] $end
$var wire 8 % in0 [7:0] $end
$var wire 1 & clk $end
$scope module Tb $end
$var wire 8 ' out [7:0] $end
$var reg 1 & clk $end
$var reg 4 ( count [3:0] $end
$var reg 8 ) in0 [7:0] $end
$var reg 8 * in1 [7:0] $end
$var reg 1 " reset $end
$var reg 2 + valid [1:0] $end
$upscope $end
$scope module mux_behav $end
$var wire 1 & clk $end
$var wire 8 , in0 [7:0] $end
$var wire 8 - in1 [7:0] $end
$var wire 1 " reset $end
$var wire 2 . valid [1:0] $end
$var reg 8 / out [7:0] $end
$var reg 1 0 selector $end
$upscope $end
$upscope $end
$enddefinitions $end
#0
$dumpvars
x0
bx /
b11 .
b0 -
b0 ,
b11 +
b0 *
b0 )
b0 (
bx '
0&
b0 %
b0 $
bx #
x"
b11 !
$end
#10000
00
b0 #
b0 '
b0 /
b11111111 %
b11111111 )
b11111111 ,
b1 $
b1 *
b1 -
1&
0"
#20000
0&
#30000
b11111110 %
b11111110 )
b11111110 ,
b10 $
b10 *
b10 -
1&
#40000
0&
#50000
10
b11111110 #
b11111110 '
b11111110 /
b11111101 %
b11111101 )
b11111101 ,
b11 $
b11 *
b11 -
1"
1&
#60000
0&
#70000
b1 (
b11 #
b11 '
b11 /
00
1&
#80000
0&
#90000
10
b11111101 #
b11111101 '
b11111101 /
1&
#100000
0&
#110000
b11 #
b11 '
b11 /
00
1&
#120000
0&
#130000
10
b11111101 #
b11111101 '
b11111101 /
1&
#140000
0&
#150000
b0 !
b0 +
b0 .
b11111100 %
b11111100 )
b11111100 ,
b100 $
b100 *
b100 -
b11 #
b11 '
b11 /
00
1&
#160000
0&
#170000
10
b1 !
b1 +
b1 .
b11111011 %
b11111011 )
b11111011 ,
b101 $
b101 *
b101 -
1&
#180000
0&
#190000
b10 !
b10 +
b10 .
b11111010 %
b11111010 )
b11111010 ,
b110 $
b110 *
b110 -
00
1&
#200000
0&
#210000
10
b11 !
b11 +
b11 .
b11111001 %
b11111001 )
b11111001 ,
b111 $
b111 *
b111 -
1&
#220000
0&
#230000
b0 !
b0 +
b0 .
b11111000 %
b11111000 )
b11111000 ,
b1000 $
b1000 *
b1000 -
b111 #
b111 '
b111 /
00
1&
#240000
0&
#250000
10
b1 !
b1 +
b1 .
b11110111 %
b11110111 )
b11110111 ,
b1001 $
b1001 *
b1001 -
1&
#260000
0&
#270000
b10 !
b10 +
b10 .
b11110110 %
b11110110 )
b11110110 ,
b1010 $
b1010 *
b1010 -
00
1&
